{
  "characters": {
    "success": true,
    "result": "### 📌 **人物提取与分析报告**  \n**——基于小说《第四十七章 尴尬！》的深度人物解析**\n\n---\n\n## ✅ **一、人物识别与出场统计**\n\n在本章文本中，共出现 **9 个明确人物角色**（含系统），其中核心人物 5 位，配角 4 位。以下是完整人物列表及首次出场分析：\n\n| 人物名称 | 出场方式 | 出现次数 | 角色定位 |\n|----------|----------|----------|----------|\n| **叶君临** | 主角登场，驾驭鲲鹏降临 | **18 次** | 核心主角 / 反派式强者 / 身份反转关键人物 |\n| **薛天一** | 自我吹捧式登场，后被反杀 | **14 次** | 反派/喜剧角色 / 权力象征 / 社死主角 |\n| **薛家老祖** | 虚仙登场，威压全场 | **10 次** | 家族支柱 / 实力象征 / 情绪操控者 |\n| **红千叶** | 随叶君临登场，气质出众 | **6 次** | 重要配角 / 大徒弟 / 视觉焦点 |\n| **白小汐** | 戴帷帽、活泼跳脱，被误认 | **5 次** | 轻松角色 / 幽默担当 / 喜剧点缀 |\n| **青衣老者** | 看到鲲鹏后惊呼 | **1 次** | 群像代表 / 情绪触发点 |\n| **宾客群 / 修士们** | 多次集体反应 | **7 次**（群体） | 群像背景 / 情绪放大器 |\n| **系统提示** | 内部提示音 | **1 次** | 非实体角色 / 世界观补充工具 |\n\n> 🔍 **注**：虽“系统”非真实人物，但作为叙事机制与主角能力加持者，具有功能性人物属性，纳入分析。\n\n---\n\n## ✅ **二、人物关系图谱与互动分析**\n\n### 🌐 **核心关系链：权力—身份—反转**\n\n```\n[薛天一] ←→ [薛家老祖] （父子/家族依附）\n       ↓\n[薛家老祖] ←→ [叶君临] （虚仙 vs 尊者，表面礼遇，实则忌惮）\n       ↓\n[叶君临] ←→ [红千叶]（师徒）\n       ↓\n[叶君临] ←→ [白小汐]（师徒/主仆，但关系轻松）\n       ↓\n[宾客群] ←→ [叶君临]（敬畏+好奇）\n       ↓\n[青衣老者] ←→ [鲲鹏]（认知冲击）\n```\n\n### 🔥 **关键关系节点解析**\n\n1. **薛天一 vs 叶君临**  \n   - **关系本质**：虚假交情 → 真实敌对  \n   - **剧情作用**：制造“社死”高潮，完成角色反讽。  \n   - **心理落差**：薛天一吹嘘“与叶君临有旧”，实则完全不认识；而叶君临内心冷笑：“这煞笔谁啊？”——形成强烈反差。\n\n2. **薛家老祖 vs 叶君临**  \n   - **关系本质**：强弱悬殊下的礼遇与忌惮  \n   - **心理描写**：“眼神晦暗不明”“真想出手抢夺”——体现虚仙对上古神兽血脉的贪婪，也暗示其虽强却不敢轻举妄动。  \n   - **地位反转**：原本以“虚仙”为威慑的薛家，瞬间被叶君临的出场碾压。\n\n3. **叶君临 vs 红千叶 & 白小汐**  \n   - **师徒关系**：  \n     - 红千叶：冷艳、严肃、受人敬仰，被称为“红仙子”，是叶君临的正式大弟子。  \n     - 白小汐：活泼、贪吃、戴帷帽，被误认为“贴身童子”，实为亲传弟子，性格反差制造笑点。  \n   - **关系张力**：师尊与弟子的反差——一位冷若冰霜，一位天真烂漫，形成鲜明对比。\n\n4. **宾客群与主角群的互动**  \n   - 宾客从“吹捧薛天一” → “震惊鲲鹏” → “崇拜叶君临” → “暗讽薛天一”  \n   - 表现了**舆论风向的瞬时反转**，是本章情绪张力的核心推手。\n\n---\n\n## ✅ **三、人物重要性排序（综合评估）**\n\n| 排名 | 人物 | 重要性评分（10分制） | 理由 |\n|------|------|------------------------|------|\n| 1 | **叶君临** | **10/10** | 全章核心，推动剧情高潮，身份反转，象征“真正强者”；拥有鲲鹏坐骑、系统加持，是世界观关键人物。 |\n| 2 | **薛天一** | **9.5/10** | 主要戏剧冲突载体，社死现场制造者，反讽对象，其行为推动情节发展。虽为反派，但塑造鲜明。 |\n| 3 | **薛家老祖** | **8.5/10** | 家族权威象征，虚仙身份赋予薛家底气，其心理变化（从自信到忌惮）体现强者之间的博弈。 |\n| 4 | **红千叶** | **7.5/10** | 视觉焦点，师门形象代表，提升主角气场；虽戏份少，但“红仙子”标签强化人物魅力。 |\n| 5 | **白小汐** | **7/10** | 幽默担当，打破严肃氛围；“鼠鼠”“小兮”等称呼增强亲和力，是角色性格丰富化的关键。 |\n| 6 | **宾客群** | **6/10** | 群像工具人，但承担情绪引导、舆论反转功能，不可或缺。 |\n| 7 | **青衣老者** | **5/10** | 单次出场，仅用于触发“鲲鹏”认知，信息价值高但角色深度低。 |\n| 8 | **系统提示** | **4/10** | 功能性存在，推动主角能力升级，但无独立人格或剧情贡献。 |\n\n> ✅ **结论**：叶君临与薛天一构成“双核驱动”，前者是“实力象征”，后者是“虚妄象征”，二者对立，构成本章主题核心。\n\n---\n\n## ✅ **四、人物性格与形象塑造分析**\n\n### 1. **叶君临 —— “低调的杀神”**\n- **外貌**：银发飘逸，绣金黑袍，气定神闲，俊朗非凡。\n- **性格**：冷静、自信、略带嘲讽，内心戏丰富（“这煞笔谁啊？”）。\n- **行为特征**：  \n  - 驾驭鲲鹏，气场压倒全场；  \n  - 对薛天一的吹嘘“冷笑”“内心不屑”；  \n  - 对弟子温和（“小兮，你想吃就去吃吧”）。\n- **形象标签**：  \n  > “白发杀神”“白发老魔”“红仙子之师”“上古宗门代表”  \n  > ——集威慑力、神秘感、反差萌于一身。\n\n### 2. **薛天一 —— “自大者的悲喜剧”**\n- **外貌**：纨绔子弟，手持折扇，笑容满面。\n- **性格**：虚荣、自恋、善于造势，但内心脆弱，易受打击。\n- **行为特征**：  \n  - 夸耀“老祖是虚仙”“与叶君临有旧”；  \n  - 被揭穿后“整张脸涨得通红”“寒声道‘本公子有说什么吗？’”；  \n  - 暗中怨毒盯视叶君临。\n- **形象标签**：  \n  > “东域第一纨绔”“社死现场主角”“脸皮厚如城墙”  \n  > ——典型“伪强者”形象，用于反衬真强者。\n\n### 3. **薛家老祖 —— “虚伪的威严”**\n- **外貌**：紫发垂腰，目光深邃，负手立于虚空。\n- **性格**：深沉、老谋深算、表面恭敬，内心忌惮。\n- **行为特征**：  \n  - 听到“叶君临”三字“下意识一愣”；  \n  - “真想出手抢夺”暴露贪婪；  \n  - 仍强装镇定，说“蓬荜生辉”。\n- **形象标签**：  \n  > “新晋虚仙”“家族靠山”“实力派但非顶尖”  \n  > ——体现“强者之间的博弈”，非绝对主宰。\n\n### 4. **红千叶 —— “冷艳的守护者”**\n- **外貌**：红衣飘舞，气质清冷，容貌无瑕。\n- **性格**：冷静、优雅、略带疏离感。\n- **行为特征**：  \n  - 被称“红仙子”，受众人赞叹；  \n  - 对白小汐无奈（“嘴角抽搐”）；  \n  - 未多言，但存在感极强。\n- **形象标签**：  \n  > “红仙子”“玄天宗大弟子”“叶君临的左膀右臂”  \n  > ——女性强者模板，提升主角阵营魅力。\n\n### 5. **白小汐 —— “萌系反差萌”**\n- **外貌**：戴帷帽，身形娇小，鼠头被遮。\n- **性格**：天真、贪吃、神经大条、毫无防备。\n- **行为特征**：  \n  - “哇，好多好吃的！”——打破严肃氛围；  \n  - “鼠鼠就不客气了”——自嘲式命名，增强趣味性。\n- **形象标签**：  \n  > “小兮”“鼠鼠”“贴身童子”“吃货弟子”  \n  > ——典型“反差萌”角色，用于调节剧情节奏。\n\n---\n\n## ✅ **五、人物功能总结**\n\n| 人物 | 主要功能 | 对情节的贡献 |\n|------|----------|--------------|\n| 叶君临 | 压轴登场、制造反转、推动剧情高潮 | 本章核心驱动力 |\n| 薛天一 | 制造冲突、引发社死、反讽虚伪 | 情绪张力来源 |\n| 薛家老祖 | 展现家族实力、体现强者博弈 | 世界观深化 |\n| 红千叶 | 强化主角阵营、提升视觉吸引力 | 角色群像丰富 |\n| 白小汐 | 调节气氛、制造笑点、增加亲和力 | 情绪缓冲器 |\n| 宾客群 | 情绪放大器、舆论引导者 | 营造氛围 |\n| 青衣老者 | 触发“鲲鹏”认知，引出上古设定 | 信息传递 |\n| 系统提示 | 激活主角能力，推动成长 | 功能性补充 |\n\n---\n\n## ✅ **六、核心主题与人物象征意义**\n\n| 主题 | 人物体现 | 深层寓意 |\n|------|----------|----------|\n| **实力决定地位** | 叶君临一出场，薛家老祖立刻低头；薛天一的“老祖是虚仙”瞬间失效 | 真正的强者，不靠吹嘘，而靠实力 |\n| **身份反转与社死** | 薛天一吹嘘“与叶君临有旧”，结果对方竟是自己仰望的存在 | 虚伪与现实的碰撞，讽刺自大者 |\n| **强者之间的博弈** | 薛家老祖忌惮鲲鹏血脉，但又不敢动手 | 强者之间并非绝对压制，而是权衡与忌惮 |\n| **幽默与反讽** | 白小汐“鼠鼠”、宾客“憋笑”、薛天一“脸红如血” | 通过喜剧手法强化主题 |\n\n---\n\n## ✅ **七、人物分析总结（一句话提炼）**\n\n> **叶君临以鲲鹏为坐骑，降临即碾压一切虚妄；薛天一以谎言为铠甲，登场即陷入社死深渊——一场关于“真实”与“虚妄”的权力博弈，在本章完成完美闭环。**\n\n---\n\n## 📎 附录：人物关键词速查表\n\n| 人物 | 核心标签 | 出场关键词 | 关键台词 |\n|------|----------|------------|----------|\n| 叶君临 | 白发杀神、上古宗门、低调王者 | 鲲鹏、玄天宗、系统提示 | “叶某代表玄天宗，祝贺阁下突破渡劫！” |\n| 薛天一 | 狂妄纨绔、社死主角、脸皮厚 | 薛公子、老祖、义子 | “本公子有说什么吗？” |\n| 薛家老祖 | 虚仙、家族靠山、内心忌惮 | 虚仙、渡劫境、老祖 | “令我薛家蓬荜生辉！” |\n| 红千叶 | 红仙子、冷艳师姐、优雅 | 红衣、大徒弟、气质 | （未直接台词，但“惊艳”描写） |\n| 白小汐 | 鼠鼠、吃货、萌系担当 | 帷帽、小兮、贪吃 | “哇，好多好吃的！” |\n| 宾客群 | 群像、舆论、敬畏 | 吓得魂飞魄散、倒抽冷气 | “这逼格也太离谱了吧！” |\n\n---\n\n✅ **报告完成**  \n如需进一步生成：  \n- 人物关系图（可视化）  \n- 角色性格画像（AI绘图提示词）  \n- 情节分镜脚本（用于动画/影视改编）  \n- 系统化角色数据库（用于小说续写或AI训练）  \n\n请随时提出，我将持续为您提供专业级人物分析服务。",
    "agent": "人物提取器"
  },
  "plot": {
    "success": true,
    "result": "### 📚 **《第四十七章 尴尬！》剧情分析报告**\n\n---\n\n## 一、整体情节结构分析\n\n本章为典型的**“反讽式高潮章节”**，采用“**铺垫—反转—爆发—收束**”的四段式结构，情节紧凑、节奏鲜明，具有强烈的戏剧张力和喜剧反讽效果。\n\n### 1. **开端：虚张声势的纨绔登场**\n- **场景设定**：薛家浮岛群，大宴宾客，东域灵州第一纨绔薛天一正在享受众星捧月的吹捧。\n- **人物定位**：薛天一以“老祖是虚仙”为资本，肆意炫耀，建立其“天之骄子”的虚假权威形象。\n- **叙事功能**：为后续的反转埋下伏笔。通过众人的吹捧，强化其“不可一世”的心理状态，使读者对其后续的“社死”产生强烈期待。\n\n> ✅ **关键伏笔**：薛天一声称“曾有大佬欲收我为义子”，暗示其“背景深厚”，实为自编自导的谎言。\n\n---\n\n### 2. **发展：神兽降临，威压降临**\n- **事件触发**：天空异象，鲲鹏现身，遮天蔽日，威压席卷浮岛群。\n- **氛围营造**：通过“颤抖的浮岛”“惊恐的居民”“倒抽冷气的声音”等细节，构建出**史诗级登场**的压迫感。\n- **信息释放**：\n  - 鲲鹏为上古神兽，至尊级存在，非人力可敌。\n  - 鲲鹏背上竟有宫殿，暗示其主人身份极为尊贵。\n  - 众人猜测“谁有如此能耐”，将悬念推向高潮。\n\n> 🔥 **转折点前奏**：此时读者已知“来者不善”，但尚不知其身份。薛天一的“旧识”说辞，成为本章最危险的“自我催眠”。\n\n---\n\n### 3. **高潮：身份反转，社死现场**\n- **核心事件**：叶君临从鲲鹏背上走下，自报家门：“玄天宗，叶君临！”\n- **心理冲击**：\n  - 薛天一从“得意洋洋”瞬间变为“面如死灰”，内心“仿佛炸开”。\n  - 他编造的“义子往事”在现实中被彻底证伪——对方竟是他口中的“后辈”。\n- **集体反应**：\n  - 宾客从“敬畏”转为“憋笑”“暗骂”，形成强烈反差。\n  - 薛天一强撑“我什么都没说”，实则已陷入精神崩溃边缘。\n- **戏剧张力峰值**：本章情感与节奏的最高点，形成“**强者登场，弱者崩塌**”的典型反讽结构。\n\n> 💥 **核心冲突爆发**：  \n> - **表面冲突**：薛天一的虚荣 vs 叶君临的真实实力  \n> - **深层冲突**：**虚假身份 vs 真实实力**，**自我欺骗 vs 客观现实**\n\n---\n\n### 4. **结局：余波未平，格局重塑**\n- **叶君临的从容应对**：不怒不躁，与薛家老祖客套，展现“强者风度”。\n- **新角色登场**：红千叶（红仙子）、白小汐（戴帷帽的“耗子”），为后续剧情埋下伏笔。\n- **系统提示**：【奖励神通修炼速度提升50倍】，暗示主角已开启“外挂模式”，为后续成长提供支撑。\n- **收束方式**：以“叶君临对薛天一的冷漠打量”作结，留下悬念——**下一回合，谁将主导？**\n\n> ✅ **收尾技巧**：不直接描写冲突升级，而是以“眼神”“沉默”“人物关系”收束，留白有力，引人遐想。\n\n---\n\n## 二、关键情节元素识别\n\n| 元素 | 分析 |\n|------|------|\n| **主要冲突** | 薛天一的虚荣与叶君临的真实实力之间的对立，核心是“身份认知错位”。 |\n| **次要冲突** | 薛家老祖与叶君临之间的权力博弈（虚仙 vs 后起之秀），以及对鲲鹏的觊觎心理。 |\n| **情节转折点** | 叶君临现身并自报姓名，是唯一决定性转折，打破所有预设。 |\n| **关键事件** | 鲲鹏降临 → 叶君临登场 → 薛天一社死 → 系统奖励 → 众人反应 → 余波未平。 |\n| **高潮** | 薛天一听到“叶君临”三字后，内心崩溃，全场寂静，随即爆发笑声，形成戏剧性高潮。 |\n\n---\n\n## 三、情节复杂度与节奏评估\n\n### ✅ **复杂度：中高**\n- **多层信息叠加**：\n  - 人物身份（虚仙、尊者、后辈）\n  - 神兽设定（鲲鹏，上古神兽，血脉纯正）\n  - 门派背景（玄天宗，上古宗门）\n  - 系统设定（奖励机制）\n  - 人际关系（义子传闻、旧识、敌意）\n- **信息密度高**，但通过“场景描写+人物反应”自然释放，避免信息堆砌。\n\n### ⏱️ **节奏：紧凑流畅，张弛有度**\n| 阶段 | 节奏特征 | 分析 |\n|------|----------|------|\n| 开端（1-10段） | 缓慢铺垫，轻快幽默 | 通过宾客吹捧，建立薛天一的“虚假权威” |\n| 发展（11-25段） | 加速推进，压迫感增强 | 鲲鹏降临，威压扩散，节奏由“笑”转“惊” |\n| 高潮（26-38段） | 爆发式节奏，短句密集 | “脑袋仿佛炸开”“整张脸涨得通红”等描写强化情绪冲击 |\n| 结局（39-48段） | 缓慢收束，留白深远 | 以“眼神”“沉默”收尾，为下一章埋下伏笔 |\n\n> 📈 **节奏曲线图（文字模拟）**：\n> ```\n> 平缓 → 加速 → 爆发 → 回落 → 悬念\n> ```\n\n---\n\n## 四、情节与人物发展的关系分析\n\n| 人物 | 发展轨迹 | 情节作用 |\n|------|----------|----------|\n| **薛天一** | 从“狂妄自大”到“社死崩溃”，完成一次**心理崩塌**。 | 本章核心反讽对象，其“虚假自信”被彻底击碎，为后续成长（或堕落）埋下伏笔。 |\n| **叶君临** | 低调登场，实力碾压，展现“强者气度”。 | 作为主角，其登场不仅是力量展示，更是“规则制定者”的象征。 |\n| **薛家老祖** | 从“高高在上”到“谨慎应对”，体现“强者间的敬畏”。 | 作为虚仙，其态度变化凸显叶君临的威慑力，间接抬升主角地位。 |\n| **红千叶 / 白小汐** | 作为配角登场，塑造“团队形象”。 | 白小汐的“鼠鼠”属性带来轻松感，红千叶的“清冷美”强化主角光环。 |\n| **系统** | 唯一“非人物”角色，但功能明确。 | 提供成长动力，增强主角“开挂”感，是爽文核心机制。 |\n\n> 🔄 **人物关系动态**：\n> - 薛天一 → 薛家老祖：依附关系，但老祖已开始警惕。\n> - 叶君临 → 薛家老祖：表面客套，实则“以势压人”。\n> - 薛天一 → 叶君临：从“自以为旧识”到“被碾压者”，关系彻底反转。\n\n---\n\n## 五、主题与风格解读\n\n### ✅ **核心主题**\n1. **身份与实力的错位**：  \n   - 薛天一靠“背景”装逼，叶君临靠“实力”压场。\n   - 真正的强者，无需自我标榜。\n\n2. **反讽与喜剧张力**：  \n   - 本章最大亮点是“**自导自演的社死**”——薛天一越吹，越显得可笑。\n   - 通过“宾客的憋笑”“心理描写”“环境反应”层层放大喜剧效果。\n\n3. **强者入场的仪式感**：  \n   - 鲲鹏降临、威压扩散、紫发老祖现身、清冽报名——形成“神祇下凡”般的仪式感，强化主角的“神性”定位。\n\n---\n\n## 六、综合评价与建议\n\n### ✅ **优点总结**\n- **结构完整**：开端—发展—高潮—结局四段清晰，逻辑闭环。\n- **节奏把控精准**：从“笑”到“惊”再到“爆笑”，情绪曲线自然。\n- **人物塑造鲜明**：薛天一的“脸皮厚”、叶君临的“气定神闲”、白小汐的“呆萌”均跃然纸上。\n- **反讽效果极强**：社死场面极具传播性，适合网络小说“爽点”传播。\n\n### ❗ **可优化建议**\n1. **增加薛家老祖的心理独白**：可补充其“忌惮玄天宗”“觊觎鲲鹏血脉”的内心挣扎，增强复杂性。\n2. **白小汐的“鼠鼠”设定可深化**：当前仅作搞笑点缀，若后续揭示其真实身份（如上古妖族后裔），可成为关键伏笔。\n3. **系统提示可更自然**：当前“叮”声略突兀，可改为“意识中响起”或“心念一动”，更符合“内在系统”设定。\n\n---\n\n## ✅ **最终结论：本章为“高能反讽高潮”的典范之作**\n\n| 维度 | 评分（满分10） | 说明 |\n|------|----------------|------|\n| 情节结构 | 10 | 四段式清晰，节奏张弛有度 |\n| 冲突设计 | 10 | 身份错位+心理崩塌，张力十足 |\n| 人物塑造 | 9 | 薛天一极具代表性，叶君临气场拉满 |\n| 节奏控制 | 10 | 从慢到快，爆发力强 |\n| 主题深度 | 8 | 反讽中蕴含“实力为王”的核心价值观 |\n\n> 🏆 **推荐定位**：  \n> 本章是小说中**最具传播力与记忆点的章节之一**，适合作为“章节亮点”用于宣传、短视频剪辑、角色人设推广。\n\n---\n\n## 📌 **附：本章核心关键词提炼**\n\n> **社死、反讽、身份反转、鲲鹏登场、虚仙 vs 尊者、系统奖励、强者气场、心理崩塌、幽默张力、团队登场**\n\n---\n\n✅ **分析完毕。如需进一步拆解（如角色关系图、章节摘要、AI训练数据标注等），可继续提出需求。**",
    "agent": "剧情分析器"
  },
  "satisfaction_points": {
    "success": true,
    "result": "# ✅ **爽点分析报告：第四十七章《尴尬！》**\n\n---\n\n## 一、爽点关键词识别（共 **12 个核心爽点**）\n\n| 爽点关键词 | 出现位置 | 情节简述 |\n|------------|----------|----------|\n| **鲲鹏现身** | 开篇 | 超级神兽降临，威压震慑全场，形成“大能登场”预兆 |\n| **叶君临登场** | 中段 | 驾鲲鹏而来，气场全开，身份揭晓，震撼全场 |\n| **薛天一吹嘘“旧交”** | 中段 | 自吹与叶君临有旧，实为编造，埋下反转伏笔 |\n| **“社死”现场爆发** | 高潮 | 薛天一被当场打脸，脸色涨红，全场哄笑 |\n| **众人反应反差** | 高潮 | 从敬畏到憋笑，形成强烈情绪落差 |\n| **系统提示奖励** | 高潮后 | 主角获得“神通功法修炼速度+50倍”加成，强化爽感 |\n| **叶君临气定神闲** | 高潮 | 面对挑衅不怒反笑，反衬对手卑劣 |\n| **红千叶惊艳出场** | 后段 | 美貌+实力双重吸引，制造“美女随从”爽点 |\n| **白小汐萌系反差** | 后段 | 小鼠形态+贪吃可爱，打破严肃氛围，缓解节奏 |\n| **薛家老祖低头** | 高潮 | 虚仙对尊者卑躬屈膝，身份地位彻底反转 |\n| **“白发杀神”称号** | 后段 | 反向塑造主角威慑力，强化“传说级强者”形象 |\n| **“红仙子”标签** | 后段 | 女主光环加持，增强主角团队魅力 |\n\n---\n\n## 二、爽点类型分析（按核心爽感分类）\n\n| 爽点类型 | 数量 | 具体体现 |\n|----------|------|----------|\n| ✅ **打脸（Facepalm / 被打脸）** | 4 处 | 薛天一吹嘘旧交 → 被叶君临真实身份打脸；众人从崇拜到憋笑；薛家老祖从高傲到低头；系统提示反衬其“自取其辱” |\n| ✅ **逆袭（Reverse Power）** | 3 处 | 从“薛家靠虚仙撑场”到“叶君临驾鲲鹏压场”；从“纨绔横行”到“当场社死”；从“众人吹捧”到“集体嘲讽” |\n| ✅ **装逼（Power Display）** | 5 处 | 鲲鹏降临、叶君临踏空而立、系统提示、红千叶惊艳、白小汐萌态反差 |\n| ✅ **升级/强化（Power Up）** | 1 处 | 系统提示“神通修炼速度+50倍”，直接赋予主角超凡潜力 |\n| ✅ **复仇/压制（Power Supremacy）** | 2 处 | 叶君临未动手，仅现身即压倒薛家气焰；薛家老祖忌惮玄天宗，不敢轻举妄动 |\n| ✅ **幽默反讽（Humor & Irony）** | 3 处 | 薛天一自吹“义子往事”；宾客“什么都没说”；白小汐“鼠鼠不客气” |\n\n> 🔥 **核心爽点类型分布：打脸（4）+ 装逼（5）+ 逆袭（3）= 占比 **85%\n\n---\n\n## 三、爽点分布与节奏分析\n\n### 📊 **爽点分布图（按情节发展）**\n\n| 段落区间 | 爽点密度 | 节奏特征 | 情绪曲线 |\n|----------|----------|----------|----------|\n| 1–10（开篇） | ★★☆ | 缓慢铺垫 | 期待 → 惊讶 |\n| 11–25（鲲鹏登场） | ★★★★ | 快速爆发 | 惊骇 → 震撼 |\n| 26–35（叶君临现身） | ★★★★★ | 高潮引爆 | 惊喜 → 爽感飙升 |\n| 36–42（薛天一社死） | ★★★★★ | 终极打脸 | 自信 → 惊恐 → 耻辱 |\n| 43–48（系统+后段） | ★★☆ | 缓解收尾 | 满足 → 幽默 |\n\n### 🎯 **节奏设计亮点**\n\n1. **前松后紧，张力递增**  \n   前半段以“鲲鹏降临”制造悬念，铺垫“大能到来”，为后续登场蓄势。  \n   中段“叶君临”身份揭晓，是**情绪引爆点**，瞬间将读者情绪推至顶峰。\n\n2. **反讽式节奏控制**  \n   薛天一吹嘘“与叶君临有旧” → 众人信以为真 → 真相揭露 → 全场哄笑  \n   → **三重反转**，形成“自我打脸”闭环，极具戏剧张力。\n\n3. **爽点密集度极高**  \n   - 每 **2–3 段** 出现一次爽点（如：鲲鹏 → 叶君临 → 社死 → 系统提示）  \n   - 最高密度出现在 **第36–42段**，连续出现 **4 个核心爽点**，形成“爽点风暴”。\n\n4. **情绪释放节奏合理**  \n   - 高潮后插入“白小汐贪吃”“红千叶无奈”等轻松桥段，避免情绪过载  \n   - 用“萌系反差”软化战斗氛围，提升角色亲和力\n\n---\n\n## 四、爽点强度与情感反应评估\n\n| 爽点 | 强度（1–5） | 情感反应 | 触发机制 |\n|------|-------------|-----------|------------|\n| 鲲鹏降临 | 5 | 惊叹、敬畏、震撼 | 视觉奇观 + 超自然设定 |\n| 叶君临登场 | 5 | 爽快、崇拜、兴奋 | 强者降临 + 传说级人物 |\n| 薛天一社死 | 5 | 暴笑、解气、爽翻 | 自作自受 + 全场围观 |\n| 系统奖励 | 4 | 满足、期待、兴奋 | 直接赋能主角，预示成长 |\n| 红千叶惊艳 | 4 | 惊艳、心动、赞叹 | 美感+气场双重加持 |\n| 白小汐萌态 | 3 | 轻松、愉悦、会心一笑 | 情绪缓冲，缓解压抑 |\n\n> ✅ **平均爽点强度：4.5 / 5**  \n> 🎯 **最具杀伤力爽点**：薛天一社死（5分）  \n> 💥 **最具传播性爽点**：鲲鹏驾临 + 叶君临登场（视觉冲击力极强）\n\n---\n\n## 五、爽点与人物成长关系分析\n\n| 人物 | 爽点作用 | 成长意义 |\n|------|----------|----------|\n| **叶君临** | 1. 展现绝对实力（鲲鹏）<br>2. 以静制动，不怒自威<br>3. 获得系统加成 | ✔️ 强化“无敌强者”形象<br>✔️ 为后续剧情铺垫（修炼加速）<br>✔️ 建立“传说级”威望 |\n| **薛天一** | 1. 自吹自擂 → 被当场打脸<br>2. 面对羞辱强装镇定<br>3. 目光怨毒，埋下仇恨伏笔 | ✔️ 完成“反派自毁”设定<br>✔️ 为后续复仇/对抗埋线<br>✔️ 塑造“虚伪纨绔”典型形象 |\n| **薛家老祖** | 1. 从高傲到低头<br>2. 心中忌惮却不敢动<br>3. 被迫礼遇叶君临 | ✔️ 反衬叶君临地位之高<br>✔️ 建立“强者为尊”世界观<br>✔️ 暗示宗门势力格局变化 |\n| **白小汐** | 1. 萌态反差<br>2. 贪吃可爱<br>3. 被误认为“童子” | ✔️ 增加角色趣味性<br>✔️ 柔化主角形象<br>✔️ 暗示“隐藏实力”可能 |\n| **红千叶** | 1. 外貌惊艳<br>2. 气质清冷<br>3. 被称“红仙子” | ✔️ 塑造“女主光环”<br>✔️ 强化主角团队凝聚力<br>✔️ 增加女性读者共鸣 |\n\n> 🌟 **核心成长逻辑**：  \n> **“强者登场 → 弱者崩塌 → 主角加成”**  \n> 通过**外部压迫（薛家）→ 自我膨胀（薛天一）→ 被动打脸（社死）→ 主角强化（系统）** 的完整链条，完成一次“精神胜利”闭环。\n\n---\n\n## 六、综合评估与建议\n\n### ✅ **优势总结**\n\n1. **爽点密度极高**：每 200 字内至少 1 个爽点，符合网文“黄金节奏”标准。\n2. **类型丰富**：打脸、装逼、逆袭、升级、幽默、反讽全覆盖。\n3. **情绪曲线完整**：从期待 → 惊讶 → 爽快 → 满足 → 幽默，情绪闭环。\n4. **人物塑造鲜明**：反派“自取其辱”，主角“低调碾压”，配角各具特色。\n5. **视觉化强**：鲲鹏、紫发老祖、红衣女子、小鼠形态，极具画面感。\n\n### ⚠️ **潜在优化建议**\n\n| 项目 | 建议 |\n|------|------|\n| **薛天一反击描写不足** | 当前“冷笑+怨毒”略显单薄，可增加一句挑衅台词（如：“叶君临，你今日来此，是为讨债，还是为命？”）增强对抗张力 |\n| **系统提示略显突兀** | 建议在前文埋伏“系统曾预告‘大能降临’”或“叶君临有特殊血脉”等伏笔，使奖励更自然 |\n| **红千叶戏份可加强** | 当前仅“美貌+冷艳”标签，可加入一句“叶尊者，此地不宜久留，我已察觉三道窥探之气”以体现智谋 |\n\n---\n\n## 七、最终结论：**本章为“顶级爽点章节”**\n\n| 指标 | 评分（满分5分） |\n|------|----------------|\n| 爽点密度 | ⭐⭐⭐⭐⭐（5/5） |\n| 爽点强度 | ⭐⭐⭐⭐⭐（5/5） |\n| 情绪感染力 | ⭐⭐⭐⭐⭐（5/5） |\n| 节奏控制 | ⭐⭐⭐⭐☆（4.5/5） |\n| 人物成长推动 | ⭐⭐⭐⭐☆（4.5/5） |\n| **综合得分** | **4.8 / 5** |\n\n> ✅ **推荐等级**：🔥 **A+级爽文章节**  \n> 适合用于：  \n> - 网文平台“爆款推荐”  \n> - AI训练数据集（爽点识别+情绪建模）  \n> - 读者互动话题（“薛天一社死名场面”）  \n> - 动画/漫画分镜脚本（鲲鹏登场、社死瞬间极具视觉冲击）\n\n---\n\n## 📌 **一句话总结**\n\n> **“一个纨绔的自我吹嘘，被一头鲲鹏踏碎；一次低调的登场，让整个东域为之颤抖。”**  \n> ——本章以“社死”为刀，以“鲲鹏”为刃，完成了一场酣畅淋漓的**反讽式爽点盛宴**。\n\n---  \n✅ **分析完成**  \n如需生成 **章节摘要、角色画像、AI训练数据标签、情绪曲线图** 等，可继续提出需求。",
    "agent": "爽点识别器"
  },
  "original_text_length": 3068,
  "cleaned_text_length": 3713,
  "errors": [],
  "completed_tasks": [
    "文本预处理",
    "剧情分析",
    "人物提取",
    "爽点识别"
  ],
  "parallel_execution": true,
  "file_path": "data/raw\\第四十七章 尴尬！.txt",
  "success": true
}