{
  "chapter_info": {
    "chapter_title": "第三十章 天帝法相显威！",
    "chapter_file": "data\\cleaned_novel\\第三十章 天帝法相显威！.txt",
    "novel_type": "玄幻",
    "processing_time": "40.2秒",
    "total_segments": 9,
    "total_scenes": 14,
    "total_storyboards": 10
  },
  "basic_stats": {
    "total_segments": 9,
    "total_scenes": 14,
    "total_storyboards": 10
  },
  "segments": [
    {
      "segment_id": "82be51a3-6319-434e-b198-dcdfdcf11d06",
      "segment_index": 0,
      "text": "第三十章 天帝法相显威！\n\n别跟这小子废话，我看他长得细皮嫩肉的，倒不如把他宰了直接吃掉！兽族族长满脸凶狠。\n\n哦？\n\n叶君临似笑非笑，身形消失原地。\n\n唰！\n\n一记重拳打去，破碎虚空，造成阵阵扭曲的涟漪。\n\n你！\n\n兽族族长惊怒，抡起狼牙棒猛烈地扫出，爆发出排山倒海的汹涌力道。\n\n轰！\n\n兽族族长倒飞出十几丈，握住狼牙棒的大手在发抖，面容呈现痛苦之状，最终忍不住哇地吐出一大口血。\n\n它的眼神，满是深深的震惊！\n\n对方朴实无华的一拳，居然差点重伤了自己？\n\n要知道，身为秘境六大王族中的兽族，在力道这方面是最为突出的。\n\n结果，在这种情况却落了下风！\n\n人族，你找死！\n\n兽族族长脾气火爆，被一拳击退后，气急败坏地发出怒吼，古老的符文瞬间在浑身环绕，散发出冲天的凶煞之气。\n\n接着，就势不可挡地冲杀而出。\n\n一起上，杀了他！\n\n其它族的族长脸上杀气腾腾，要么是使用天赋神通，或者祭出祖传的法宝。",
      "metadata": {
        "dialogue_count": 0,
        "action_count": 5,
        "environment_count": 1,
        "character_mentions": [
          "兽族族长",
          "天帝",
          "叶君临"
        ],
        "previous_segment_summary": "",
        "next_segment_preview": "轰轰轰！\n\n刹那间。\n\n铺天盖地的能量波动席卷，方圆万里的山林都在震动。\n\n此时，叶君临孤身一人，跟...",
        "segment_index": 0
      },
      "scenes": [
        {
          "scene_id": 1,
          "scene_description": "兽族族长在战斗前暴怒挑衅，叶君临从容应对，瞬间爆发一拳击退对手，展现惊人实力。",
          "environment": "荒芜的秘境战场，地面裂痕纵横，天空阴云密布，雷光隐现，远处有残破的古老石柱与断裂的符文阵纹。",
          "atmosphere": "紧张压抑，杀机四伏，天地仿佛因即将爆发的战斗而震颤。",
          "time": "黄昏时分，天边残阳如血，但云层厚重，光线昏暗。",
          "characters": [
            {
              "name": "兽族族长",
              "appearance": "体型魁梧，面部布满兽类特征，尖耳利齿，眼神深邃威严，皮肤呈暗褐色带鳞片或毛发纹理。身着兽皮与金属镶嵌的战甲，肩部饰骨质图腾，腰间悬挂兽首权杖，披风破旧而威严。",
              "expression": "满脸凶狠，嘴角咧开露出獠牙，瞳孔收缩，充满杀意。",
              "action": "怒吼挑衅，握紧狼牙棒，准备发动攻击。",
              "emotion": "暴怒、轻蔑、嗜血"
            },
            {
              "name": "叶君临",
              "appearance": "白发如雪，面容冷峻，眉目深邃，眼神如渊，身形修长，气质孤傲压迫。玄色长袍绣银纹，腰束玉带，披风猎猎，肩扛古剑，步履间似有风雷隐动。",
              "expression": "似笑非笑，嘴角微扬，眼神平静如渊。",
              "action": "身形瞬间消失，随后一拳轰出，破空而至。",
              "emotion": "从容、冷静、压迫感十足"
            }
          ],
          "main_action": "叶君临以瞬移之术突袭，一拳击破虚空，造成空间涟漪，重创兽族族长。",
          "emotional_tone": "压迫与震惊交织，紧张感迅速攀升。",
          "importance_score": 9,
          "visual_suitability": 10,
          "transition_cue": "兽族族长倒飞出十几丈，口中喷血，眼神震惊，怒吼‘人族，你找死！’",
          "segment_index": 0,
          "scene_index_in_segment": 0,
          "visual_narrative": {
            "visual_description": "特写镜头聚焦于叶君临的面部与上半身，他白发如雪，发丝在无形风中微微飘动，眉心微蹙，右眉轻轻上扬，眼中闪过一丝意外与玩味。眼神深邃如渊，映着背景中流转的金色光辉，瞳孔中似有雷光隐现。玄色长袍绣银纹，衣襟随风猎猎，肩扛古剑，剑身隐有裂纹般的符文微闪。腰间玉带泛着冷光，披风边缘被金色光晕勾勒出轮廓。他微微侧首，嘴角勾起一抹似笑非笑的弧度，仿佛在审视一场出乎意料的戏码。",
            "composition": {
              "shot_type": "特写",
              "angle": "微仰",
              "layout": "画面中央为叶君临的面部与上半身，背景虚化为流动的金色光纹与暗金天幕，形成强烈对比，突出人物的孤傲与压迫感。",
              "focus": "面部表情与眼神"
            },
            "characters": [],
            "environment": {
              "background": "虚化的金色光纹在暗金与紫灰交织的天幕中流动，背景中隐约可见六族族长的轮廓与族徽微光，但已模糊成光晕",
              "atmosphere": "神圣而神秘，带有治愈与压迫并存的双重气息，仿佛天地在为一场大战做准备，静谧中暗藏风暴",
              "lighting": "主光源来自背景金色光辉，柔和却具有穿透力，面部受光均匀，但眼窝与下颌投下深邃阴影，增强压迫感",
              "color_scheme": "主色调为暗金、紫灰与玄黑，点缀银白与微红，形成冷峻与神圣交织的视觉张力"
            },
            "style": {
              "art_style": "中国玄幻风格，融合水墨晕染与数字绘画的高精度渲染，强调角色神态与光影层次",
              "quality_tags": "8K, ultra-detailed, cinematic lighting, dynamic composition, dramatic contrast, ethereal glow",
              "additional_details": "发丝与披风边缘有微弱电弧闪烁，暗示其体内蕴含未释放的雷意；背景光纹中隐约浮现古老天帝法相的残影"
            },
            "narration": {
              "scene_description": "黄昏将尽，罗天秘境核心区域，虚空裂隙间弥漫着古老而神圣的金色光辉。六族族长在光芒中恢复伤势，气息节节攀升，仿佛天地为他们重铸战魂。",
              "inner_monologue": "呦，还自带奶妈回血？这六族，倒真会藏一手。",
              "emotional_text": "他眸光微动，冷峻的面容下，是风暴前的寂静。一场看似团结的复苏，却在他眼中，悄然裂开一道缝隙。",
              "transition_text": "而就在这神圣的光辉中，叶君临的嘴角，轻轻扬起——一场无声的博弈，才刚刚开始。"
            },
            "storyboard_suggestions": {
              "panel_type": "单格",
              "dialogue_position": "上方",
              "effects": "无特效",
              "page_layout": "标准布局"
            },
            "scene_id": 1
          }
        },
        {
          "scene_id": 2,
          "scene_description": "兽族族长被重创后怒火中烧，激发古老符文，释放凶煞之气，准备全力反扑，其他族长随之响应，局势全面升级。",
          "environment": "战场中心区域，地面因冲击波龟裂，空气中弥漫着血腥与符文能量的波动，雷光在云层中闪烁，仿佛天地共怒。",
          "atmosphere": "杀意滔天，战意沸腾，整个空间仿佛被点燃，充满毁灭气息。",
          "time": "与前一场景连续，仍为黄昏，但天色愈发阴沉，仿佛末日将至。",
          "characters": [
            {
              "name": "兽族族长",
              "appearance": "体型魁梧，面部布满兽类特征，尖耳利齿，眼神深邃威严，皮肤呈暗褐色带鳞片或毛发纹理。身着兽皮与金属镶嵌的战甲，肩部饰骨质图腾，腰间悬挂兽首权杖，披风破旧而威严。",
              "expression": "面容扭曲，双眼赤红，嘴角溢血，怒火中烧，充满杀意。",
              "action": "怒吼后全身符文环绕，凶煞之气冲天而起，猛然冲杀而出。",
              "emotion": "暴怒、不甘、决死"
            },
            {
              "name": "其他族族长",
              "appearance": "各具异族特征，或身披鳞甲，或头戴骨冠，或手持异宝，服饰各异但皆透着古老与威压。",
              "expression": "脸上杀气腾腾，眼神凶狠，充满敌意。",
              "action": "纷纷发动天赋神通或祭出祖传法宝，准备围攻叶君临。",
              "emotion": "贪婪、杀意、群起而攻"
            }
          ],
          "main_action": "兽族族长激发古老符文，释放凶煞之气，怒冲而上；其余族长响应，集体发动攻击，形成围杀之势。",
          "emotional_tone": "全面爆发，群战前奏，压迫感与危机感达到顶峰。",
          "importance_score": 10,
          "visual_suitability": 10,
          "transition_cue": "‘一起上，杀了他！’的怒吼声响起，其他族长纷纷出手，战斗全面升级。",
          "segment_index": 0,
          "scene_index_in_segment": 1,
          "visual_narrative": {
            "visual_description": "石族族长半身像特写，面部肌肉紧绷，眉心古老纹路在昏暗天光下泛着微弱青光，双目如炬凝视前方，瞳孔中映着尚未散去的金色符文残影。暗红色长袍褶皱翻卷，肩披镶晶石披风被余波撕裂一角，晶石碎片闪烁寒芒。腰间骨质图腾饰物裂开一道缝隙，隐约透出内部幽蓝脉动。右臂肌肉虬结，掌心朝前，掌纹间残留着与叶君临余波对撞后留下的焦黑灼痕。背景为一道扭曲的风暴边缘，地面龟裂如蛛网，远处符文残影如鬼火飘荡，但整体虚化，仅作氛围衬托。光线来自天际雷云，冷蓝与暗金交织，勾勒出他古铜色皮肤的棱角与沧桑轮廓。",
            "composition": {
              "shot_type": "特写",
              "angle": "微仰",
              "layout": "角色居中，上半身占据画面主体，背景虚化处理，仅保留能量风暴的边缘轮廓与残余符文光痕",
              "focus": "面部表情与眉心纹路"
            },
            "characters": [],
            "environment": {
              "background": "虚化的战场中央，地面龟裂如蛛网，空中残留着未散的金色符文残影，远处雷云翻涌，天色如墨，仅余一线黄昏残光",
              "atmosphere": "危机四伏，压抑中透出一丝短暂的默契与警觉，六族联盟的脆弱平衡初现端倪",
              "lighting": "冷蓝与暗金交织的天光从上方斜射，形成强烈的明暗对比，突出面部轮廓与眉心纹路的神圣感",
              "color_scheme": "主色调为暗红、古铜、冷蓝与幽金，整体偏暗沉，但眉心与晶石处有微弱光芒点缀"
            },
            "style": {
              "art_style": "中国玄幻风，融合写实主义与东方神祇美学，强调角色神态与服饰细节的史诗感",
              "quality_tags": "8K高清，超精细纹理，电影级光影，角色表情张力十足，背景虚化处理得当",
              "additional_details": "眉心纹路中隐约浮现远古石族图腾的微光，暗示其血脉与天地共鸣；掌心焦痕中似有符文残影挣扎欲现"
            },
            "narration": {
              "scene_description": "风暴未息，余波如刀，撕裂苍穹。石族族长以血肉之躯，硬撼天帝之威，护住濒死的木族族长。六族联盟的裂痕，在这一刻被强行缝合，却也埋下更深的裂痕。",
              "inner_monologue": "——我以骨为盾，以血为契。今日之忍，非为退让，而是为六族存续，为那一丝未灭的希望。",
              "emotional_text": "他不是英雄，却在最黑暗的时刻，成了唯一能站住的人。那道伤痕，是代价，也是誓言。",
              "transition_text": "可当叶君临的杀招再度降临，六族的短暂同盟，能否抵挡这来自天帝法相的无情审判？"
            },
            "storyboard_suggestions": {
              "panel_type": "单格",
              "dialogue_position": "上方",
              "effects": "无特效",
              "page_layout": "标准布局"
            },
            "scene_id": 2
          }
        }
      ]
    },
    {
      "segment_id": "ec442252-4c22-4324-9fce-f70b2af51d45",
      "segment_index": 1,
      "text": "轰轰轰！\n\n刹那间。\n\n铺天盖地的能量波动席卷，方圆万里的山林都在震动。\n\n此时，叶君临孤身一人，跟六族族长陷入激战。\n\n其中羽族族长眼神冰冷，浑身银色羽毛散发辉芒，宛如坚不可摧的神兵利器。\n\n唰，它的身形迅疾如风，挥出羽翼就要将叶君临斩成两半！\n\n当~\n\n金铁交击声刺耳。\n\n叶君临脸色如常，抬起手掌挥去，裹挟着无匹的劲气击退了羽族族长。\n\n接着他抬拳迅猛地打出，拳芒蕴含澎湃的法力真元，压得各大族族长喘不过气来。\n\n老夫来挡你！\n\n石族族长怒吼。\n\n漆黑色光晕在体表盛烈，荡漾出肉眼可见的圈圈波纹。\n\n嘭的炸响！\n\n石族族长一声闷哼，眼睛流露出些许痛苦之色。\n\n呵呵，还挺抗打。叶君临冷笑，这一拳他没有任何保留，可见对方的肉身防御堪称恐怖。\n\n换做是严长老，早就被一拳打爆了！\n\n各位不要慌，只要我们配合默契，杀了这个人族是迟早的事！",
      "metadata": {
        "dialogue_count": 0,
        "action_count": 4,
        "environment_count": 1,
        "character_mentions": [
          "羽族族长",
          "石族族长",
          "叶君临",
          "严长老"
        ],
        "previous_segment_summary": "第三十章 天帝法相显威！\n\n别跟这小子废话，我看他长得细皮嫩肉的，倒不如把他宰了直接吃掉！兽族族长满...",
        "next_segment_preview": "木族族长低喝，密密麻麻的藤蔓撕裂虚空，符文交织缠绕，每根藤蔓都可媲美三品灵器，实力极强。",
        "segment_index": 1
      },
      "scenes": [
        {
          "scene_id": 1,
          "scene_description": "叶君临孤身迎战六族族长，首度展现天帝法相威能，与羽族族长展开激烈交锋。",
          "environment": "方圆万里山林，林木参天，地动山摇，能量波动如潮水般席卷四周，天空被撕裂出裂痕，灵气狂暴翻涌，地面龟裂，碎石飞舞。",
          "atmosphere": "肃杀、紧张、压迫感极强，天地仿佛在为这场大战震颤，充满毁灭与爆发的前兆。",
          "time": "黄昏时分，天际残阳如血，云层翻滚，雷光隐现，似有天劫将至。",
          "characters": [
            {
              "name": "叶君临",
              "appearance": "白发如雪，面容冷峻，眉目深邃，眼神如渊，身形修长，气质孤傲压迫。玄色长袍绣银纹，腰束玉带，披风猎猎，肩扛古剑，步履间似有风雷隐动。",
              "expression": "冷峻中带着讥诮，嘴角微扬，似笑非笑，眼神锐利如刀。",
              "action": "身形骤然消失，瞬移至羽族族长身侧，一拳轰出，拳芒撕裂虚空，造成空间扭曲。",
              "emotion": "从容不迫，战意盎然，略带轻蔑"
            },
            {
              "name": "羽族族长",
              "appearance": "面容清冷，眉目如画，双眸深邃似含星河，发色如雪，垂至腰际，身形修长。银白羽纹长袍，衣袂飘逸，肩披羽翼状披风，腰间缀有族徽玉佩。",
              "expression": "眼神冰冷，杀意凛然，嘴角微扬露出残忍笑意。",
              "action": "身形如风般疾掠，双翼展开，羽芒闪烁，挥动羽翼欲斩叶君临为两半。",
              "emotion": "凶狠、嗜血、充满杀意"
            }
          ],
          "main_action": "叶君临以瞬移之术突袭羽族族长，一拳轰出，拳芒撕裂虚空，击退羽族族长，展现其恐怖战力。",
          "emotional_tone": "紧张、压迫、爆发前的凝滞感",
          "importance_score": 9,
          "visual_suitability": 10,
          "transition_cue": "轰轰轰！刹那间，铺天盖地的能量波动席卷，方圆万里的山林都在震动。",
          "segment_index": 1,
          "scene_index_in_segment": 0,
          "visual_narrative": null
        },
        {
          "scene_id": 2,
          "scene_description": "叶君临与六族族长全面交战，石族族长主动迎击，展现其惊人的肉身防御力。",
          "environment": "战场中心，地面塌陷成深坑，碎石与尘土在能量风暴中翻腾，空中漂浮着残破的羽翼与石纹符印，灵气如刀锋般切割空气。",
          "atmosphere": "混乱、激烈、生死一线，战斗已进入白热化阶段，各方势力拼尽全力。",
          "time": "与前一场景连续，天色渐暗，雷云密布，仿佛天地共怒。",
          "characters": [
            {
              "name": "叶君临",
              "appearance": "白发如雪，面容冷峻，眉目深邃，眼神如渊，身形修长，气质孤傲压迫。玄色长袍绣银纹，腰束玉带，披风猎猎，肩扛古剑，步履间似有风雷隐动。",
              "expression": "面无表情，眼神锐利如鹰，嘴角微扬，似在评估对手。",
              "action": "抬拳迅猛打出，拳芒蕴含澎湃法力真元，压迫各大族族长，逼得他们喘不过气。",
              "emotion": "冷静、掌控全局、战意滔天"
            },
            {
              "name": "石族族长",
              "appearance": "面容苍老，眉骨突出，眉心有古老纹路，眼神深邃沉稳，身材高大挺拔，肤色古铜。暗红色族长长袍，绣有石族图腾，肩披镶晶石披风，腰间悬挂骨质图腾饰物。",
              "expression": "怒吼咆哮，眉头紧锁，眼中闪过痛苦之色，但依旧咬牙硬抗。",
              "action": "怒吼迎战，体表浮现漆黑色光晕，波纹荡漾，硬接叶君临一拳。",
              "emotion": "愤怒、坚韧、不屈"
            }
          ],
          "main_action": "叶君临全力一拳轰击石族族长，后者虽被震退并痛苦闷哼，但未被击溃，展现出恐怖的肉身防御力。",
          "emotional_tone": "激烈、震撼、生死搏杀的压迫感",
          "importance_score": 10,
          "visual_suitability": 10,
          "transition_cue": "呵呵，还挺抗打。叶君临冷笑，这一拳他没有任何保留，可见对方的肉身防御堪称恐怖。",
          "segment_index": 1,
          "scene_index_in_segment": 1,
          "visual_narrative": null
        },
        {
          "scene_id": 3,
          "scene_description": "六族族长在叶君临的强势压制下，开始组织战术配合，试图以团队协作击败叶君临。",
          "environment": "战场边缘，六族族长呈包围之势，各自释放族中秘法，符文闪烁，灵力交织成网，试图封锁叶君临行动空间。",
          "atmosphere": "紧张、策略性对抗，从个体激战转向团队协作，气氛从混乱转为有组织的压迫。",
          "time": "与前一场景连续，夜幕降临，星河隐现，天地间仿佛有某种古老意志在注视。",
          "characters": [
            {
              "name": "叶君临",
              "appearance": "白发如雪，面容冷峻，眉目深邃，眼神如渊，身形修长，气质孤傲压迫。玄色长袍绣银纹，腰束玉带，披风猎猎，肩扛古剑，步履间似有风雷隐动。",
              "expression": "目光扫视六族族长，神情淡漠，似在嘲弄他们的徒劳。",
              "action": "静立原地，气息收敛，仿佛在等待对手的下一步动作。",
              "emotion": "冷静、不屑、掌控全局"
            },
            {
              "name": "羽族族长",
              "appearance": "面容清冷，眉目如画，双眸深邃似含星河，发色如雪，垂至腰际，身形修长。银白羽纹长袍，衣袂飘逸，肩披羽翼状披风，腰间缀有族徽玉佩。",
              "expression": "眼神冰冷，略带忌惮，但依旧冷声下令。",
              "action": "冷声提醒其他族长，试图组织战术配合。",
              "emotion": "警惕、谋略、不甘"
            },
            {
              "name": "石族族长",
              "appearance": "面容苍老，眉骨突出，眉心有古老纹路，眼神深邃沉稳，身材高大挺拔，肤色古铜。暗红色族长长袍，绣有石族图腾，肩披镶晶石披风，腰间悬挂骨质图腾饰物。",
              "expression": "喘息未定，眼中仍存痛楚，但已恢复镇定。",
              "action": "点头回应，与其他族长交换眼神，准备协同作战。",
              "emotion": "痛苦但坚定，意志不屈"
            },
            {
              "name": "其他族长（未具名）",
              "appearance": "六族族长集体登场，各具异象，灵力波动交织成阵。",
              "expression": "神情凝重，眼神交汇，传递战术信号。",
              "action": "彼此呼应，释放族中秘法，形成初步合击阵势。",
              "emotion": "紧张、协作、求胜心切"
            }
          ],
          "main_action": "六族族长在叶君临的强势压制下，开始组织战术配合，试图以团队协作击败叶君临，形成围攻之势。",
          "emotional_tone": "紧张、策略对抗、压迫感升级",
          "importance_score": 8,
          "visual_suitability": 9,
          "transition_cue": "各位不要慌，只要我们配合默契，杀了这个人族是迟早的事！",
          "segment_index": 1,
          "scene_index_in_segment": 2,
          "visual_narrative": {
            "visual_description": "特写镜头聚焦于叶君临的面部与上半身，他白发如雪，随风轻扬，发丝间似有雷光隐现。眉目深邃如渊，双眸冰冷如寒星，瞳孔中倒映着战场崩塌的残影与血雾翻涌的天际。嘴角微扬，带着一丝近乎残酷的笑意，仿佛在欣赏猎物的挣扎。玄色长袍绣银纹，衣袂在无形风雷中猎猎翻飞，腰间玉带泛起微光，肩扛古剑的剑柄上缠绕着断裂的符文残片。背景为一片漆黑的虚空，仅有一道裂痕般的天际余光从乌云缝隙中透出，映照在他冷峻的侧脸与肩头，形成强烈的明暗对比。整体画面充满压迫感与神性威压，仿佛天地失序皆因他而起。",
            "composition": {
              "shot_type": "特写",
              "angle": "微仰",
              "layout": "角色占据画面中心，面部与肩部占画面约70%，背景极简，仅以暗色裂痕天幕为衬，突出人物气势",
              "focus": "面部表情与眼神"
            },
            "characters": [],
            "environment": {
              "background": "乌云密布的夜空裂痕，天际最后一丝光亮被吞噬，背景仅余一片深邃的黑暗与几缕漂浮的血雾残符",
              "atmosphere": "杀机四伏，天地失序，压迫感极强，仿佛整个世界都在为他的存在而颤抖",
              "lighting": "侧逆光，从乌云缝隙中透出一束惨白冷光，斜照在叶君临面部与肩部，形成强烈的光影对比，突出其孤傲与威压",
              "color_scheme": "主色调为深黑与玄银，点缀冷白与暗金，营造出神性与毁灭交织的视觉张力"
            },
            "style": {
              "art_style": "中国玄幻风格，融合水墨晕染与数字高精度渲染，人物细节极致，背景留白有力，具有史诗级视觉冲击",
              "quality_tags": "8K超清，电影级光影，细节丰富，角色表情张力十足，构图极具戏剧性",
              "additional_details": "风雷在叶君临脚下隐约浮现，剑柄上的符文残片微微闪烁，暗示其力量尚未完全释放"
            },
            "narration": {
              "scene_description": "夜幕将至，天地崩裂，六族联盟在叶君临的连环杀招下节节败退。山体崩塌，灵脉断裂，血雾与残破符文在空中漂浮，仿佛世界末日已至。",
              "inner_monologue": "——你们的挣扎，不过是我棋局中的一粒尘埃。天帝法相，已为我所承。这天地，终将臣服于我之剑下。",
              "emotional_text": "绝望如潮水般淹没六族族长的心神，而叶君临，却如神祇降临，冷眼俯视众生的哀鸣。",
              "transition_text": "就在这万籁俱寂的死寂中，一道纯净的治愈之光，悄然从天而降，照向羽族族长——命运的转折，才刚刚开始。"
            },
            "storyboard_suggestions": {
              "panel_type": "单格",
              "dialogue_position": "上方",
              "effects": "无特效",
              "page_layout": "标准布局"
            },
            "scene_id": 3
          }
        }
      ]
    },
    {
      "segment_id": "cb12ef37-4237-4953-bcb9-f93dc5978bf3",
      "segment_index": 2,
      "text": "木族族长低喝，密密麻麻的藤蔓撕裂虚空，符文交织缠绕，每根藤蔓都可媲美三品灵器，实力极强。\n\n是吗？\n\n下一秒。\n\n叶君临使出大荒囚天指，四根巨指齐刷刷地戳去，每根手指头都金灿灿的，威势浩荡无边。\n\n呃啊……\n\n上千条藤蔓纷纷断裂，木族族长如遭雷击。\n\n好在余波被石族族长挡住，这才避免了陨落的风险。\n\n接着，叶君临杀招频出，接连击伤各族的族长！\n\n好强。\n\n羽族族长额头溢出冷汗，身上撕裂性的伤口在流血。\n\n突然。\n\n一道治愈系的光芒照耀着它，浑身的伤口迅速愈合起来。\n\n小看我们六族，是要付出代价的！\n\n角族族长宛若犀牛怪，头顶尖锐的独角，独角有金色的圣光在闪烁，散发出令人祥和宁静的气息。\n\n嗡嗡嗡~",
      "metadata": {
        "dialogue_count": 0,
        "action_count": 1,
        "environment_count": 0,
        "character_mentions": [
          "木族族长",
          "石族族长",
          "角族族长",
          "叶君临",
          "羽族族长"
        ],
        "previous_segment_summary": "轰轰轰！\n\n刹那间。\n\n铺天盖地的能量波动席卷，方圆万里的山林都在震动。\n\n此时，叶君临孤身一人，跟...",
        "next_segment_preview": "很快，其它族的族长都沐浴在光芒内，不仅伤势痊愈，还精神百倍起来。\n\n呦，还自带奶妈回血？\n\n叶君临有...",
        "segment_index": 2
      },
      "scenes": [
        {
          "scene_id": 1,
          "scene_description": "叶君临面对木族族长的藤蔓攻势，以大荒囚天指强势破防，展现压倒性实力。",
          "environment": "方圆万里山林剧烈震动，虚空被撕裂，藤蔓如巨蟒般从地底破土而出，符文交织成网，笼罩战场中央。",
          "atmosphere": "肃杀、紧张、能量波动剧烈，天地仿佛在战栗，空间扭曲，灵气狂暴。",
          "time": "黄昏时分，天边残阳如血，云层翻滚，雷光隐现。",
          "characters": [
            {
              "name": "木族族长",
              "appearance": "面容沉稳，眉目深邃，银发垂肩，身形高大，气质威严，眼神锐利如刀。身着深青色族长长袍，绣有木纹图腾，腰佩古玉符印，肩披兽皮披风。",
              "expression": "眉头紧锁，眼神震惊中带着不甘",
              "action": "低喝发动藤蔓攻势，操控上千条符文藤蔓撕裂虚空",
              "emotion": "震惊、愤怒、忌惮"
            },
            {
              "name": "叶君临",
              "appearance": "白发如雪，面容冷峻，眉目深邃，眼神如渊，身形修长，气质孤傲压迫。身着玄色长袍绣银纹，腰束玉带，披风猎猎，肩扛古剑，步履间似有风雷隐动。",
              "expression": "面无表情，眼神凌厉如刀锋",
              "action": "施展大荒囚天指，四根金光灿灿的手指齐戳而出",
              "emotion": "冷静、压迫、杀意隐现"
            }
          ],
          "main_action": "叶君临以大荒囚天指击溃木族族长的藤蔓攻势，上千条藤蔓瞬间断裂，木族族长遭受重创。",
          "emotional_tone": "压迫、震撼、力量碾压",
          "importance_score": 9,
          "visual_suitability": 10,
          "transition_cue": "下一秒，叶君临杀招频出，战局迅速升级",
          "segment_index": 2,
          "scene_index_in_segment": 0,
          "visual_narrative": null
        },
        {
          "scene_id": 2,
          "scene_description": "木族族长遭重创后，石族族长及时出手拦截余波，避免其陨落，六族联盟初现危机应对。",
          "environment": "战场中央能量余波如风暴般扩散，地面龟裂，碎石飞溅，空中符文残影未散。",
          "atmosphere": "危机四伏，紧张中带着一丝喘息，六族之间短暂的默契浮现。",
          "time": "与前一场景连续，仍为黄昏，但天色渐暗，雷云更浓。",
          "characters": [
            {
              "name": "木族族长",
              "appearance": "面容沉稳，眉目深邃，银发垂肩，身形高大，气质威严，眼神锐利如刀。身着深青色族长长袍，绣有木纹图腾，腰佩古玉符印，肩披兽皮披风。",
              "expression": "脸色苍白，嘴角溢血，眼神惊魂未定",
              "action": "被叶君临一击震退，险些陨落，被石族族长及时接住",
              "emotion": "惊惧、后怕、愤怒"
            },
            {
              "name": "石族族长",
              "appearance": "面容苍老，眉骨突出，眉心有古老纹路，眼神深邃沉稳，身材高大挺拔，肤色古铜。身着暗红色族长长袍，绣有石族图腾，肩披镶晶石披风，腰间悬挂骨质图腾饰物。",
              "expression": "眉头紧锁，神情凝重，双目如炬",
              "action": "猛然出手，以身躯硬接叶君临的余波，护住木族族长",
              "emotion": "警惕、担当、隐忍"
            }
          ],
          "main_action": "石族族长以肉身硬抗叶君临的攻击余波，成功救下木族族长，展现六族间短暂的协作。",
          "emotional_tone": "危机中的团结，压抑中的警觉",
          "importance_score": 8,
          "visual_suitability": 9,
          "transition_cue": "接着，叶君临杀招频出，接连击伤各族族长",
          "segment_index": 2,
          "scene_index_in_segment": 1,
          "visual_narrative": null
        },
        {
          "scene_id": 3,
          "scene_description": "叶君临连环出击，击伤羽族、角族等其余族长，六族联盟全面陷入被动，战局彻底倾斜。",
          "environment": "战场全面崩塌，山体崩裂，灵脉断裂，空中漂浮着残破符文与血雾，天地失序。",
          "atmosphere": "杀机四伏，压迫感极强，六族族长节节败退，士气低落。",
          "time": "夜幕降临前，天际最后一丝光亮被乌云吞噬。",
          "characters": [
            {
              "name": "叶君临",
              "appearance": "白发如雪，面容冷峻，眉目深邃，眼神如渊，身形修长，气质孤傲压迫。身着玄色长袍绣银纹，腰束玉带，披风猎猎，肩扛古剑，步履间似有风雷隐动。",
              "expression": "眼神冰冷，嘴角微扬，似在享受战斗的快意",
              "action": "连环施展杀招，身形如鬼魅穿梭于六族族长之间",
              "emotion": "冷酷、自信、掌控全局"
            },
            {
              "name": "羽族族长",
              "appearance": "面容清冷，眉目如画，双眸深邃似含星河，发色如雪，垂至腰际，身形修长。身着银白羽纹长袍，衣袂飘逸，肩披羽翼状披风，腰间缀有族徽玉佩。",
              "expression": "额头渗出冷汗，双眸惊恐，嘴角溢血",
              "action": "被叶君临击中，身上出现撕裂性伤口，血流不止",
              "emotion": "恐惧、震惊、无力"
            },
            {
              "name": "角族族长",
              "appearance": "面容苍老，眉骨突出，眼神深邃，身材高瘦，面部有明显疤痕，头发灰白且凌乱。身着破旧的兽皮长袍，肩披族纹图腾披风，腰间系有骨制饰物，脚踏草编鞋。",
              "expression": "神情痛苦，但眼神坚定，独角闪烁圣光",
              "action": "头顶尖角释放金色圣光，试图抵御攻击，但被击退",
              "emotion": "痛苦、倔强、不甘"
            }
          ],
          "main_action": "叶君临连续发动致命攻击，击伤羽族族长与角族族长，六族族长全面陷入被动，联盟岌岌可危。",
          "emotional_tone": "绝望、压迫、逆境中的挣扎",
          "importance_score": 10,
          "visual_suitability": 10,
          "transition_cue": "突然，一道治愈系的光芒照耀着羽族族长，浑身伤口迅速愈合",
          "segment_index": 2,
          "scene_index_in_segment": 2,
          "visual_narrative": null
        },
        {
          "scene_id": 4,
          "scene_description": "羽族族长被治愈，六族联盟重燃斗志，角族族长发动圣光独角攻击，六族合力反击的前奏。",
          "environment": "战场中央光芒骤现，一道柔和却耀眼的治愈之光从天而降，笼罩羽族族长，伤口迅速愈合，血迹消失。",
          "atmosphere": "希望与反击的前兆，从绝望中升起一丝生机，六族气息开始凝聚。",
          "time": "夜幕初临，星辰微现，天地间仿佛有某种古老意志苏醒。",
          "characters": [
            {
              "name": "羽族族长",
              "appearance": "面容清冷，眉目如画，双眸深邃似含星河，发色如雪，垂至腰际，身形修长。身着银白羽纹长袍，衣袂飘逸，肩披羽翼状披风，腰间缀有族徽玉佩。",
              "expression": "眼神从惊恐转为坚定，嘴角浮现一丝冷笑",
              "action": "被治愈光芒笼罩，伤口瞬间愈合，重新站起",
              "emotion": "震惊、感激、重燃战意"
            },
            {
              "name": "角族族长",
              "appearance": "面容苍老，眉骨突出，眼神深邃，身材高瘦，面部有明显",
              "expression": "未知表情",
              "action": "未知动作",
              "emotion": "未知情绪"
            }
          ],
          "main_action": "未知动作",
          "emotional_tone": "未知情绪",
          "importance_score": 5,
          "visual_suitability": 5,
          "transition_cue": "无转换提示",
          "segment_index": 2,
          "scene_index_in_segment": 3,
          "visual_narrative": {
            "visual_description": "特写镜头聚焦于羽族族长的面部与上半身，她双眸深邃如星河倒映，雪白长发在微风中轻扬，发丝间泛着淡淡的银光。她的面容清冷中透出一丝震撼，嘴角微微上扬，浮现出一抹冷笑，眼神从惊恐转为坚定，仿佛灵魂被重新点燃。银白羽纹长袍的衣袂在无形气流中飘动，肩披的羽翼状披风边缘闪烁着微弱的光晕，腰间族徽玉佩在光芒中微微发亮。她的伤口已完全愈合，肌肤如新生般光滑，唯有那双眸中仍残留着战斗的余烬与不屈的意志。背景为夜幕初临的战场，星辰微现，天际一道柔和却耀眼的治愈之光从天而降，仅在她周身形成光晕，其余皆隐于暗影之中。",
            "composition": {
              "shot_type": "特写",
              "angle": "微仰",
              "layout": "角色居中，面部与上半身占据画面主体，背景虚化为流动的星光与淡金色光晕，突出人物的神圣感与力量觉醒。",
              "focus": "面部与双眸"
            },
            "characters": [],
            "environment": {
              "background": "夜空为底，星辰稀疏，天际裂开一道缝隙，柔和的治愈之光从缝隙中倾泻而下，其余区域为深邃暗蓝与墨黑交织。",
              "atmosphere": "希望与反击的前兆，天地仿佛在低语，古老意志悄然苏醒，战局的天平正悄然倾斜。",
              "lighting": "主光源为自上而下的治愈之光，柔和却不容忽视，形成人物面部的高光轮廓，背景则为低光环境，形成强烈明暗对比。",
              "color_scheme": "主色调为银白、星蓝与暗金，治愈光带呈淡金色，玉佩与羽翼边缘泛着微光，整体色调冷峻中透出神圣感"
            },
            "style": {
              "art_style": "中国玄幻风格，融合日式赛璐璐与写实光影，强调角色神态与服装细节的精致刻画。",
              "quality_tags": "8K高清，超精细纹理，角色表情张力十足，光影层次丰富，动态光效自然",
              "additional_details": "发丝与衣袂有微弱的光粒子飘散，玉佩中似有星河流转，背景星光随角色情绪微微闪烁"
            },
            "narration": {
              "scene_description": "夜幕低垂，星辰初现，一道自天穹裂隙中倾泻而下的治愈之光，如神谕般降临战场中央。羽族族长的身影被光芒包裹，伤痕尽消，血迹褪去，仿佛从死寂中重生。",
              "inner_monologue": "——原来，绝望并非终点。我曾以为此战已无生路，可天意未绝，我亦未死。这一战，我必亲手撕碎命运的枷锁。",
              "emotional_text": "希望如星火燎原，从她眼中点燃。那抹冷笑，不是嘲讽，而是战神苏醒前的低语。",
              "transition_text": "天地间，六族的气息悄然凝聚，战鼓未响，却已听见命运的回音——反击，已然开始。"
            },
            "storyboard_suggestions": {
              "panel_type": "单格",
              "dialogue_position": "上方",
              "effects": "无特效",
              "page_layout": "标准布局"
            },
            "scene_id": 4
          }
        }
      ]
    },
    {
      "segment_id": "7f0d0780-8457-43cf-8a62-be19566406e1",
      "segment_index": 3,
      "text": "很快，其它族的族长都沐浴在光芒内，不仅伤势痊愈，还精神百倍起来。\n\n呦，还自带奶妈回血？\n\n叶君临有些意外。\n\n这六族族长是罗天秘境里最顶端的战力，体内有来自上古血脉的传承，以及各自赖以生存的天赋宝术。\n\n合力围攻之下，可谓是取长补短，攻势密不透风，几乎没有破绽。\n\n面对这种形势，想必就算是大乘境来了，都会感到有些棘手。\n\n或许，这就是它们如此有把握的原因！\n\n看到了吗？你是斗不过我们的！乖乖受死吧！兽族族长狞笑，试图瓦解叶君临的斗志。\n\n要换做是其他合体境强者，深陷这种困局还真的会慌。\n\n只可惜，它们在叶君临的脸上，看不到半点紧张的神情。\n\n甚至在嘴角上，还挂着一道玩味的笑意。\n\n也罢，正好试试这次的签到奖励。",
      "metadata": {
        "dialogue_count": 0,
        "action_count": 0,
        "environment_count": 0,
        "character_mentions": [
          "兽族族长",
          "罗天秘境",
          "叶君临"
        ],
        "previous_segment_summary": "木族族长低喝，密密麻麻的藤蔓撕裂虚空，符文交织缠绕，每根藤蔓都可媲美三品灵器，实力极强。",
        "next_segment_preview": "打定主意，叶君临双眼微眯，整个人的气势瞬间变了，眼神蕴含威严之意。\n\n轰！！！\n\n恐怖的气势从身上骤...",
        "segment_index": 3
      },
      "scenes": [
        {
          "scene_id": 1,
          "scene_description": "六族族长在光芒中恢复伤势并提升精神状态，叶君临意外察觉其异常能力。",
          "environment": "罗天秘境核心区域，虚空裂隙间弥漫着古老而神圣的金色光辉，地面残破但符文闪烁，背景中隐约可见六族族长的轮廓与各自族徽的微光。",
          "atmosphere": "神圣而神秘，带有治愈与压迫并存的双重气息，仿佛天地在为一场大战做准备。",
          "time": "黄昏将尽，天际泛起暗金与紫灰交织的天光，似是时间凝滞的瞬间。",
          "characters": [
            {
              "name": "叶君临",
              "appearance": "白发如雪，面容冷峻，眉目深邃，眼神如渊，身形修长，气质孤傲压迫。玄色长袍绣银纹，腰束玉带，披风猎猎，肩扛古剑，步履间似有风雷隐动。",
              "expression": "微微挑眉，眼中闪过一丝意外与玩味",
              "action": "静立于战场中央，目光扫过六族族长，观察其状态变化",
              "emotion": "惊讶中带着审视与好奇"
            },
            {
              "name": "六族族长（集体）",
              "appearance": "各自特征鲜明：兽族族长体型魁梧，面部布满兽类特征，尖耳利齿，眼神深邃威严，皮肤呈暗褐色带鳞片或毛发纹理；其余族长亦各具异象，皆身披族系象征战甲，肩挂权杖或图腾。",
              "expression": "痛苦转为舒缓，脸上浮现恢复后的振奋与自信",
              "action": "沐浴在金色光芒中，体内血脉波动，伤势迅速愈合，气息节节攀升",
              "emotion": "欣喜、自信、略带轻蔑"
            }
          ],
          "main_action": "六族族长在神秘光芒中集体恢复伤势并精神焕发，叶君临察觉其异常能力并产生疑问。",
          "emotional_tone": "意外与微妙的紧张交织，带有试探与反讽的潜流",
          "importance_score": 8,
          "visual_suitability": 9,
          "transition_cue": "叶君临轻声自语：‘呦，还自带奶妈回血？’",
          "segment_index": 3,
          "scene_index_in_segment": 0,
          "visual_narrative": null
        },
        {
          "scene_id": 2,
          "scene_description": "兽族族长挑衅叶君临，试图瓦解其斗志，展现六族联军的绝对优势与压迫感。",
          "environment": "战场中心，虚空被撕裂出巨大裂痕，地面焦黑龟裂，符文残迹闪烁，六族族长呈环形包围叶君临，形成压迫性阵势。",
          "atmosphere": "压抑、肃杀，充满杀意与心理战的张力，仿佛整个空间都在为即将到来的爆发蓄力。",
          "time": "与前一场景连续，时间未变，但气氛急剧升温。",
          "characters": [
            {
              "name": "兽族族长",
              "appearance": "体型魁梧，面部布满兽类特征，尖耳利齿，眼神深邃威严，皮肤呈暗褐色带鳞片或毛发纹理。身着兽皮与金属镶嵌的战甲，肩部饰骨质图腾，腰间悬挂兽首权杖，披风破旧而威严。",
              "expression": "狞笑，嘴角咧开，露出森然利齿，眼神充满蔑视与戏谑",
              "action": "猛然踏前一步，声震虚空，发出挑衅宣言",
              "emotion": "得意、轻蔑、充满压迫感"
            },
            {
              "name": "叶君临",
              "appearance": "白发如雪，面容冷峻，眉目深邃，眼神如渊，身形修长，气质孤傲压迫。玄色长袍绣银纹，腰束玉带，披风猎猎，肩扛古剑，步履间似有风雷隐动。",
              "expression": "嘴角微扬，笑意玩味，眼神平静如渊，毫无惧意",
              "action": "静立原地，目光直视兽族族长，未有丝毫退缩",
              "emotion": "从容、自信、略带戏谑"
            },
            {
              "name": "六族族长（集体）",
              "appearance": "各族族长皆身披族系战甲，气息凝练如刀，环形阵势中符文交织，形成无形压力场。",
              "expression": "神情冷峻，目光锁定叶君临，充满战意与必胜信念",
              "action": "齐齐凝神，阵势微动，气息合流，形成压迫性战力场",
              "emotion": "自信、团结、战意沸腾"
            }
          ],
          "main_action": "兽族族长当众挑衅叶君临，试图心理压制；六族族长合力施压，形成绝对围攻之势。",
          "emotional_tone": "压迫与反制并存，心理博弈激烈，充满张力与对抗感",
          "importance_score": 9,
          "visual_suitability": 10,
          "transition_cue": "叶君临轻声自语：‘也罢，正好试试这次的签到奖励。’",
          "segment_index": 3,
          "scene_index_in_segment": 1,
          "visual_narrative": null
        }
      ]
    },
    {
      "segment_id": "615e9ea4-b401-4577-9b34-835bc0d4045e",
      "segment_index": 4,
      "text": "打定主意，叶君临双眼微眯，整个人的气势瞬间变了，眼神蕴含威严之意。\n\n轰！！！\n\n恐怖的气势从身上骤然爆发。\n\n霎时，有道浩瀚的虚影从背后冲天而起，那对狭长的金炽眸子，漠然冰冷，披肩的长发如星河垂挂，身上的帝袍蕴含诸天星斗，包罗万象，\n\n祂头戴古老的帝冠，脑后悬挂的白色光晕，仿佛要照亮世间，驱赶无尽的黑暗。\n\n此乃天帝法相！！\n\n这，这是……\n\n六族族长满脸的骇然，浑身如坠深渊般寒冷，觉得自己是何等的渺小，面对这一尊浩瀚虚影有种臣服的感觉。\n\n当庞大的天帝法相出现时，那股恐怖的威压犹如浪潮蔓延。\n\n似乎连空间和时间都要被冻结，原始森林许多生灵都吓得匍匐在地，面露惊恐之色。\n\n这个异变，也让还在探险的荒州修士，目光都忍不住吸引了过去。",
      "metadata": {
        "dialogue_count": 0,
        "action_count": 1,
        "environment_count": 1,
        "character_mentions": [
          "天帝",
          "叶君临",
          "荒州"
        ],
        "previous_segment_summary": "很快，其它族的族长都沐浴在光芒内，不仅伤势痊愈，还精神百倍起来。\n\n呦，还自带奶妈回血？\n\n叶君临有...",
        "next_segment_preview": "天啊，那是什么？！\n\n他们喉咙咕噜吞咽口水，吓得遍体生寒，肝胆欲裂。\n\n此乃法相神通！是一种大神通之...",
        "segment_index": 4
      },
      "scenes": [
        {
          "scene_id": 1,
          "scene_description": "叶君临决定施展天帝法相，气势骤变，引发天地异象。",
          "environment": "原始森林深处，天地间弥漫着淡淡的灵光与古老气息，林木参天，枝叶间透出微弱天光，地面草木微颤，空间隐隐波动。",
          "atmosphere": "肃穆、压抑中蕴含神圣威压，仿佛天地在屏息等待某种神祇降临。",
          "time": "黄昏时分，天边残霞如血，但法相显现后，天地仿佛陷入永恒的静默。",
          "characters": [
            {
              "name": "叶君临",
              "appearance": "白发如雪，面容冷峻，眉目深邃，眼神如渊，身形修长，玄色长袍绣银纹，腰束玉带，肩扛古剑，披风猎猎，步履间似有风雷隐动。",
              "expression": "双眼微眯，神情凝重而威严，嘴角略带冷意。",
              "action": "凝神蓄势，体内灵力奔涌，双目骤然迸发金光，全身气势猛然攀升。",
              "emotion": "冷静、决然，带着掌控一切的压迫感。"
            }
          ],
          "main_action": "叶君临凝聚心神，激发体内沉睡的天帝血脉，准备显化天帝法相。",
          "emotional_tone": "肃杀、压迫、神圣不可侵犯",
          "importance_score": 9,
          "visual_suitability": 10,
          "transition_cue": "轰！！！",
          "segment_index": 4,
          "scene_index_in_segment": 0,
          "visual_narrative": null
        },
        {
          "scene_id": 2,
          "scene_description": "天帝法相破空而出，浩瀚虚影降临，威压震慑四方。",
          "environment": "原始森林上空，空间被撕裂出一道金色裂痕，虚影自裂痕中冲天而起，星斗流转，雷光缠绕，林间草木尽数伏地，天地仿佛失序。",
          "atmosphere": "神圣、浩瀚、令人窒息，仿佛宇宙初开，神祇降世。",
          "time": "与前一场景无缝衔接，法相显现后，时间仿佛凝固。",
          "characters": [
            {
              "name": "天帝法相",
              "appearance": "面容威严，眉心有天纹，眼神深邃如渊，身形高大，周身雷光缭绕，身着金色龙纹帝袍，肩披云纹披风，腰悬天命玉玺，脚踏九重祥云，脑后悬挂白色光晕，披肩长发如星河垂挂，帝袍上蕴含诸天星斗，包罗万象。",
              "expression": "漠然冰冷，俯视众生，无悲无喜，却蕴含无上威严。",
              "action": "从虚空中冲出，身躯拔地而起，双眸睁开，金炽光芒扫视四方。",
              "emotion": "神圣、不可侵犯、主宰一切。"
            },
            {
              "name": "六族族长",
              "appearance": "各族领袖，身着族中至宝服饰，面容各异，但此刻皆显惊骇。",
              "expression": "满脸骇然，瞳孔收缩，脸色苍白，身体微微颤抖。",
              "action": "本能后退，跪伏于地，额头触地，不敢直视法相。",
              "emotion": "恐惧、敬畏、臣服，如蝼蚁面对苍穹。"
            },
            {
              "name": "荒州修士",
              "appearance": "黑发垂肩，深灰色长袍，腰悬古朴玉佩，披风轻扬，气质孤傲神秘。",
              "expression": "目光骤然凝滞，瞳孔微缩，神情震惊。",
              "action": "停下探险步伐，抬头望向天际，目光被法相牢牢吸引。",
              "emotion": "震惊、震撼、难以置信。"
            }
          ],
          "main_action": "天帝法相彻底显化，浩瀚威压席卷天地，六族族长与荒州修士皆被震慑。",
          "emotional_tone": "震撼、敬畏、窒息感、神圣压迫",
          "importance_score": 10,
          "visual_suitability": 10,
          "transition_cue": "当庞大的天帝法相出现时，那股恐怖的威压犹如浪潮蔓延。",
          "segment_index": 4,
          "scene_index_in_segment": 1,
          "visual_narrative": null
        }
      ]
    },
    {
      "segment_id": "e1907606-004b-4130-85a9-fe4f5c7e1279",
      "segment_index": 5,
      "text": "天啊，那是什么？！\n\n他们喉咙咕噜吞咽口水，吓得遍体生寒，肝胆欲裂。\n\n此乃法相神通！是一种大神通之术！\n\n欧阳锋惊得眼珠子几乎要瞪出，喃喃道：究竟是谁施展出来？难道是叶天君……\n\n不远处。\n\n红千叶怔住了。\n\n那对标志的丹凤眼，流露出惊疑之色。\n\n是那家伙的手段吗？\n\n饶是他见多识广，都没见过这种类型的法相！\n\n之前佛门的法相跟这比起来，简直就是一坨狗屎！\n\n就算当初自己在中域的时候，见识过各种强者施展出法相。\n\n但在这一尊法相面前，统统都上不了台面，只有主动臣服的份！\n\n连天地万物，都黯然失色！\n\n此时。\n\n叶君临身负天帝法相，感受到身上发生的巨大变化，心里十分满意。\n\n目光扫向惊骇绝伦的六族族长，嘴角掀起一抹冷酷的笑容。",
      "metadata": {
        "dialogue_count": 1,
        "action_count": 0,
        "environment_count": 1,
        "character_mentions": [
          "红千叶",
          "天帝",
          "叶君临",
          "欧阳锋"
        ],
        "previous_segment_summary": "打定主意，叶君临双眼微眯，整个人的气势瞬间变了，眼神蕴含威严之意。\n\n轰！！！\n\n恐怖的气势从身上骤...",
        "next_segment_preview": "哼！\n\n叶君临猛地甩了下袖袍，磅礴的罡风平地而起。\n\n唰，羽族族长被高高卷起，挣扎着要逃窜，但是很快...",
        "segment_index": 5
      },
      "scenes": [
        {
          "scene_id": 1,
          "scene_description": "叶君临觉醒天帝法相，威压震慑全场，六族族长与红千叶震惊于其法相之威，欧阳锋惊骇欲绝。",
          "environment": "荒芜战场，天地间雷云翻滚，地面裂痕纵横，远处山峦崩塌，天地灵气剧烈波动，仿佛空间都在震颤。",
          "atmosphere": "肃杀、压抑、神圣与恐怖交织，天地仿佛被一股不可抗拒的威压所主宰，万物臣服于那浩瀚虚影之下。",
          "time": "黄昏将尽，天际残阳如血，云层中雷光闪烁，天地间弥漫着一种末日降临般的压迫感。",
          "characters": [
            {
              "name": "叶君临",
              "appearance": "白发如雪，面容冷峻，眉目深邃，眼神如渊，身形修长，气质孤傲压迫。玄色长袍绣银纹，腰束玉带，披风猎猎，肩扛古剑，步履间似有风雷隐动。",
              "expression": "冷峻中带着一丝满意，嘴角微扬，眼神漠然俯视众生。",
              "action": "立于战场中央，背负浩瀚天帝法相，气势如渊，缓缓环视四周。",
              "emotion": "自信、威严、掌控一切的冷酷"
            },
            {
              "name": "欧阳锋",
              "appearance": "面容阴鸷冷峻，眉骨突出，眼神锐利如鹰，留长须，身形瘦削挺拔，透出阴冷气息。深灰色长袍，厚重古朴，领口镶银边，袖口绣暗纹，腰系皮带，肩披兽皮披风。",
              "expression": "瞳孔骤缩，眼珠几乎要瞪出，嘴角抽搐，脸色惨白。",
              "action": "后退半步，双手紧握成拳，喉结剧烈滚动，喃喃自语。",
              "emotion": "惊骇、恐惧、难以置信"
            },
            {
              "name": "红千叶",
              "appearance": "面容清丽，赤发如血，眼神灵动似火，身形纤细修长，气质神秘动人。赤红长裙绣樱花纹，肩披薄纱，腰系玉铃，行走轻响如风。",
              "expression": "丹凤眼微睁，瞳孔收缩，神情凝重，似有惊疑与震撼交织。",
              "action": "怔立原地，目光死死锁定叶君临背后的天帝法相，微微张口。",
              "emotion": "震惊、震撼、难以置信，夹杂一丝复杂情绪"
            },
            {
              "name": "六族族长",
              "appearance": "未具体描写，但可推断为各族首领，衣着各异，皆为强者，气质各异但皆显卑微。",
              "expression": "面如土色，嘴唇发抖，浑身颤抖，眼中充满恐惧。",
              "action": "集体后退，有人跪地，有人捂住口鼻，有人瘫坐于地。",
              "emotion": "肝胆欲裂、恐惧至极、灵魂战栗"
            }
          ],
          "main_action": "叶君临觉醒天帝法相，浩瀚虚影冲天而起，威压震慑全场，六族族长与红千叶、欧阳锋等人目睹此景，震惊失态。",
          "emotional_tone": "震撼、压迫、神圣与恐怖并存，带有强烈的威压感与命运转折的肃穆感。",
          "importance_score": 10,
          "visual_suitability": 10,
          "transition_cue": "叶君临目光扫向惊骇绝伦的六族族长，嘴角掀起一抹冷酷的笑容。",
          "segment_index": 5,
          "scene_index_in_segment": 0,
          "visual_narrative": null
        }
      ]
    },
    {
      "segment_id": "ba4f056e-e19f-491e-82ba-3dc0fe2b4f5e",
      "segment_index": 6,
      "text": "哼！\n\n叶君临猛地甩了下袖袍，磅礴的罡风平地而起。\n\n唰，羽族族长被高高卷起，挣扎着要逃窜，但是很快就察觉到可怕的力量笼罩全身。\n\n救我！快救我啊啊啊！\n\n嘭的一声，羽族族长被无形的大手抓得爆碎，血水洋洋洒洒。\n\n各族的族长瞠目结舌，这踏马就死了？\n\n不好！兽族族长内心发毛，它看到叶君临的目光扫向自己，顿时有种大难临头的感觉。\n\n你也给我死！\n\n叶君临一拳轰出，金黄色的拳芒贯穿天地。\n\n啊……\n\n兽族族长还想负隅顽抗，结果被直接打成血雾，弥漫在了空气中。\n\n逃！快逃！！\n\n剩下的四族族长吓得亡魂皆冒，纷纷施展秘术，哪怕燃烧生命，都迫切地逃离此地。\n\n还想跑？\n\n全都给我死！！\n\n叶君临背负天帝法相，有种通天彻地之威能，手掌猛地一拉扯，恐怖的吸力瞬息爆发。",
      "metadata": {
        "dialogue_count": 0,
        "action_count": 2,
        "environment_count": 1,
        "character_mentions": [
          "羽族族长",
          "兽族族长",
          "天帝",
          "叶君临"
        ],
        "previous_segment_summary": "天啊，那是什么？！\n\n他们喉咙咕噜吞咽口水，吓得遍体生寒，肝胆欲裂。\n\n此乃法相神通！是一种大神通之...",
        "next_segment_preview": "什么？！\n\n各族族长面露绝望，身形都忍不住倒退回去。\n\n各位，干脆跟他拼了！！\n\n石族族长怒吼，散发...",
        "segment_index": 6
      },
      "scenes": []
    },
    {
      "segment_id": "36b57d4d-3d57-4398-a838-f2e676009a1c",
      "segment_index": 7,
      "text": "什么？！\n\n各族族长面露绝望，身形都忍不住倒退回去。\n\n各位，干脆跟他拼了！！\n\n石族族长怒吼，散发出巍峨的气势，发疯地冲向那道黑袍身影。\n\n烂石头，这里面就你最硬。\n\n叶君临冷笑，遥遥地点出一指。\n\n轰！\n\n金色的指芒粉碎虚空，威能浩大无边。\n\n天帝法相附带神通之一，截天指！\n\n不……石族族长发出惨叫声，浑身被霸道的金色指芒击碎，就连重组的碎石都成了齑粉，再无复生的可能。\n\n饶命，前辈饶命啊！！\n\n见状，鳞族族长，角族族长，木族族长不敢再有反抗的心思了，纷纷惊恐地求饶。\n\n叶君临懒得多废话，直接一巴掌一个全都拍死！\n\n当现场恢复平静后。\n\n叶君临收起天帝法相，感受到体内消耗掉的八成法力，咂舌道：虽然这玩意用起来爽，但特别费蓝啊！",
      "metadata": {
        "dialogue_count": 1,
        "action_count": 0,
        "environment_count": 0,
        "character_mentions": [
          "天帝",
          "木族族长",
          "石族族长",
          "角族族长",
          "鳞族族长",
          "叶君临"
        ],
        "previous_segment_summary": "哼！\n\n叶君临猛地甩了下袖袍，磅礴的罡风平地而起。\n\n唰，羽族族长被高高卷起，挣扎着要逃窜，但是很快...",
        "next_segment_preview": "接下来，该办正事了。\n\n叶君临扫视四周，皱起眉头，嗯？那只耗子呢？\n\n只见那只原本受伤趴在地面的白毛...",
        "segment_index": 7
      },
      "scenes": []
    },
    {
      "segment_id": "19d970f7-0ced-46e6-b2fa-261b31fca190",
      "segment_index": 8,
      "text": "接下来，该办正事了。\n\n叶君临扫视四周，皱起眉头，嗯？那只耗子呢？\n\n只见那只原本受伤趴在地面的白毛鼠，不知什么时候已经消失得无影无踪。",
      "metadata": {
        "dialogue_count": 0,
        "action_count": 0,
        "environment_count": 0,
        "character_mentions": [
          "白毛鼠",
          "叶君临"
        ],
        "previous_segment_summary": "什么？！\n\n各族族长面露绝望，身形都忍不住倒退回去。\n\n各位，干脆跟他拼了！！\n\n石族族长怒吼，散发...",
        "next_segment_preview": "",
        "segment_index": 8
      },
      "scenes": []
    }
  ],
  "errors": []
}