{
  "chapter_info": {
    "chapter_title": "第一章 遇强则强",
    "chapter_file": "data\\cleaned_novel\\第一章 遇强则强.txt",
    "novel_type": "玄幻",
    "processing_time": "35.7秒",
    "total_segments": 10,
    "total_scenes": 14,
    "total_storyboards": 10
  },
  "basic_stats": {
    "total_segments": 10,
    "total_scenes": 14,
    "total_storyboards": 10
  },
  "segments": [
    {
      "segment_id": "a5fa03fc-1cd1-44bc-8497-fd22cb926797",
      "segment_index": 0,
      "text": "第一章 遇强则强\n\n东域。\n\n玄天宗。\n\n一个白发及腰，身穿黑袍的年迈老者拄着拐杖，不敢置信地望着倒映在湖面上那张沧桑的脸庞，嘴里直接爆了粗口：\n\n“卧槽！！”\n\n叶君临做梦都没想到，他只是上课偷偷睡觉，醒来后居然发现自己穿越了。\n\n看着湖面上那张布满皱纹的老脸，叶君临气得浑身都在发抖，红着眼睛悲愤地喊道：\n\n“这踏马还有天理吗？”\n\n别人穿越，都是世家大族的青年才俊，或者是一方圣地的圣子，要么帅得惊天动地，再差点也就相貌平平。\n\n结果到他这里，却是个暮气沉沉的臭老头？\n\n通过记忆了解到，这个世界叫做昆仑界，以修行者为尊，什么御剑飞行，移山填海不在话下。\n\n而这具身体的原主人，是东域荒州六大宗门之一，玄天宗缥缈峰峰主。",
      "metadata": {
        "dialogue_count": 1,
        "action_count": 1,
        "environment_count": 1,
        "character_mentions": [
          "东域",
          "缥缈峰",
          "玄天宗",
          "荒州",
          "叶君临",
          "缥缈峰峰主"
        ],
        "previous_segment_summary": "",
        "next_segment_preview": "他在宗门备受尊崇，曾经更是天资卓越，年纪轻轻就修炼到金丹期，后来因为在一次清剿邪修行动时，遭到偷袭丹...",
        "segment_index": 0
      },
      "scenes": [
        {
          "scene_id": 1,
          "scene_description": "叶君临穿越后首次意识到自身处境，面对湖中倒影的震惊与愤怒。",
          "environment": "一处静谧的湖畔，湖面如镜，倒映着天空与周围山林，远处有缥缈峰轮廓隐约可见，湖边青石斑驳，草木稀疏，氛围清幽而略带神秘。",
          "atmosphere": "寂静中透着一丝诡异，湖面无风却泛起微澜，仿佛天地在回应主角的觉醒，带有玄幻世界的超然气息。",
          "time": "清晨，薄雾未散，天光微亮，晨曦透过云层洒下淡金色光晕。",
          "characters": [
            {
              "name": "叶君临",
              "appearance": "白发如雪，面容冷峻，眉目深邃，眼神如渊，身形修长，气质孤傲压迫。身着玄色长袍绣银纹，腰束玉带，披风猎猎，肩扛古剑，步履间似有风雷隐动。",
              "expression": "震惊、难以置信，随后转为悲愤与怒火，双目赤红，嘴角抽搐。",
              "action": "猛然从湖边石上起身，踉跄后退，双手颤抖地抓向湖面倒影，随后猛然抬头怒吼。",
              "emotion": "震惊 → 愤怒 → 悲愤"
            }
          ],
          "main_action": "叶君临在湖边醒来，目睹湖中倒影为一名白发苍老的男子，震惊于自己穿越成一名垂暮老者，情绪崩溃并爆发怒吼。",
          "emotional_tone": "震惊、荒诞、愤怒、悲愤交织，带有强烈的反差感与戏剧张力。",
          "importance_score": 9,
          "visual_suitability": 9,
          "transition_cue": "湖面涟漪骤然扩散，倒影中浮现一道模糊身影，仿佛来自缥缈峰的低语，暗示后续剧情展开。",
          "segment_index": 0,
          "scene_index_in_segment": 0,
          "visual_narrative": {
            "visual_description": "特写镜头聚焦于叶君临的面部与上半身，他白发如雪，发丝在风中微微飘动，眉心微蹙，眼神深邃如渊，透着一丝惊疑与试探。他的嘴角略带讥诮，似笑非笑，仿佛在嘲弄命运，又似在试探未知。玄色长袍绣银纹，领口与袖口泛着暗光，玉带束腰，披风猎猎，肩扛古剑，骨杖拄地，斑驳的纹理在残阳下泛出幽冷金属光泽。背景为荒凉山巅，云雾缭绕，天边残阳如血，金橙与暗红交织，远处山峦模糊如剪影，古庙废墟若隐若现。光线从右侧斜照，勾勒出他冷峻轮廓，面部阴影深邃，瞳孔中似有微光闪烁，仿佛灵魂在低语。",
            "composition": {
              "shot_type": "特写",
              "angle": "微仰",
              "layout": "角色居中，面部与上半身占据画面主体，背景虚化，仅保留天际线与云雾轮廓，突出人物孤绝气质",
              "focus": "面部表情与眼神细节"
            },
            "characters": [],
            "environment": {
              "background": "荒凉山巅，云雾缭绕，天边残阳如血，远处山峦起伏，隐约可见古庙废墟的残垣断壁",
              "atmosphere": "压抑而神秘，仿佛天地都在为宿主的生死倒计时，风声低吟，寂静中暗藏杀机",
              "lighting": "斜侧逆光，夕阳余晖从右上方洒落，勾勒出人物轮廓，面部一半沐浴在金橙光中，一半隐于暗影，形成强烈对比",
              "color_scheme": "暗红、金橙、玄黑、银灰为主色调，冷暖交织，营造末日苍凉与神秘张力"
            },
            "style": {
              "art_style": "中国玄幻风格，融合赛博朋克光影与水墨意境，人物线条刚毅，细节精致，具有电影级质感",
              "quality_tags": "8K超清，细节丰富，光影层次分明，角色表情生动，背景虚化自然",
              "additional_details": "面部微光闪烁，暗示系统正在运行；骨杖与古剑上隐约浮现微弱符文，暗示其不凡来历"
            },
            "narration": {
              "scene_description": "荒凉山巅，残阳如血，天地寂静。风在耳边低语，仿佛在为一个即将觉醒的灵魂默哀。叶君临立于绝境，白发如雪，眸光如渊，肩扛古剑，骨杖拄地，仿佛一尊从远古走来的孤神。",
              "inner_monologue": "‘系统……你真能改声音？’——我本想试探，却不知，这荒诞的玩笑，竟成了命运的开关。",
              "emotional_text": "荒诞中藏着锋芒，戏谑下是孤注一掷的期待。他笑，不是因为轻松，而是因为——他已无路可退。",
              "transition_text": "就在他话音未落，系统那轻快俏皮的提示音骤然响起：‘叮——已为您切换至‘萝莉音’模式，欢迎使用！’——刹那间，天地仿佛静止，风停，云凝，连那残阳也似在颤抖。"
            },
            "storyboard_suggestions": {
              "panel_type": "单格",
              "dialogue_position": "上方",
              "effects": "无特效",
              "page_layout": "标准布局"
            },
            "scene_id": 1
          }
        },
        {
          "scene_id": 2,
          "scene_description": "叶君临通过记忆融合，确认自身身份与所处世界，初步建立世界观认知。",
          "environment": "湖畔静地，背景中缥缈峰若隐若现，云雾缭绕，山势起伏，隐约可见宗门建筑轮廓，整体环境空灵而古老。",
          "atmosphere": "神秘、压抑、略带压迫感，仿佛整个天地都在注视着这位新觉醒的‘峰主’。",
          "time": "清晨，雾气渐散，阳光穿透云层，洒在湖面与山巅。",
          "characters": [
            {
              "name": "叶君临",
              "appearance": "白发如雪，面容冷峻，眉目深邃，眼神如渊，身形修长，气质孤傲压迫。身着玄色长袍绣银纹，腰束玉带，披风猎猎，肩扛古剑。",
              "expression": "从愤怒转为凝重，眼神逐渐沉静，眉头紧锁，似在快速消化信息。",
              "action": "双手撑地，闭目沉思，脑海中浮现记忆碎片，包括宗门名称、身份背景、修行体系等。",
              "emotion": "震惊后转为冷静与警觉，内心开始重构认知。"
            }
          ],
          "main_action": "叶君临通过融合原主记忆，确认自己穿越至昆仑界，成为东域荒州玄天宗缥缈峰峰主，了解世界规则与自身处境。",
          "emotional_tone": "冷静、警觉、略带压抑，情绪从爆发转向深思，为后续成长埋下伏笔。",
          "importance_score": 10,
          "visual_suitability": 8,
          "transition_cue": "记忆碎片中浮现‘玄天宗’三字，同时远处传来钟声，悠远而沉重，仿佛召唤。",
          "segment_index": 0,
          "scene_index_in_segment": 1,
          "visual_narrative": {
            "visual_description": "特写镜头聚焦于叶君临的面部与上半身，他白发凌乱地贴在汗湿的额角，眉心紧锁，瞳孔因震惊而剧烈收缩，仿佛能映出天际最后一丝残红。嘴角微颤，冷汗从鬓角滑落，滴在玄袍领口，泛起细微水渍。他右手紧握骨杖，指节发白，手背青筋暴起如虬龙盘绕；左手死死按在古剑剑柄上，指甲几乎嵌入剑鞘。玄袍被狂风撕扯，银纹在暗光中若隐若现，仿佛有灵性般微微震颤。背景为一片虚化的山巅边缘，碎石与风沙在远处模糊飞舞，天色如血溃散，云层翻涌如巨兽咆哮。光线从右侧斜切而来，将他的侧脸勾勒成一道冷峻的剪影，瞳孔深处却燃起一簇近乎疯狂的火光。",
            "composition": {
              "shot_type": "特写",
              "angle": "微仰",
              "layout": "角色居中，面部与肩部占据画面三分之二，背景虚化处理，仅保留天际一线残光与翻滚云层的轮廓",
              "focus": "角色面部与右手骨杖的交界处，突出情绪张力与生命倒计时的压迫感"
            },
            "characters": [],
            "environment": {
              "background": "虚化的山巅边缘，碎石与风沙在远处模糊飞舞，天际仅余一线残红，云层如墨翻涌，似有天地共震之象",
              "atmosphere": "危机四伏，生死一线，空气中弥漫着压迫感与倒计时般的窒息感",
              "lighting": "侧逆光，残阳余晖从右上方斜照，形成强烈明暗对比，面部一半浸在阴影中，一半被血色光芒灼烧",
              "color_scheme": "主色调为暗红与玄黑，点缀银白与冷蓝（来自系统光效的微弱反光），整体呈现压抑而炽烈的视觉张力"
            },
            "style": {
              "art_style": "中国玄幻风 × 数码幻想美学，融合水墨晕染与高精度CG渲染",
              "quality_tags": "8K超清，电影级光影，细节极致，角色表情张力拉满，背景虚化自然",
              "additional_details": "骨杖表面浮现细微裂纹，似与叶君临生命共鸣；古剑剑柄上隐约有符文闪烁，与系统光效形成微弱呼应"
            },
            "narration": {
              "scene_description": "暮色如血，山巅将倾。风在耳畔嘶吼，天地仿佛在为一个将死之人倒数。一小时，仅剩一小时——命运的钟摆，悬于生死之间。",
              "inner_monologue": "……一小时？不可能！我还没活够！既然天不让我死，那就让我——战到最后一息！碰瓷强者？好！哪怕拼尽此身，也要搏出一条生路！",
              "emotional_text": "绝望如冰，却在心火中炸裂。不是屈服，是觉醒。当生命只剩一瞬，真正的强者，才刚刚开始。",
              "transition_text": "骨杖落地，一声轻响，却如惊雷炸裂天际。叶君临，动了。他不再等死，而是——迎向风暴。"
            },
            "storyboard_suggestions": {
              "panel_type": "单格",
              "dialogue_position": "上方",
              "effects": "无特效",
              "page_layout": "标准布局"
            },
            "scene_id": 2
          }
        }
      ]
    },
    {
      "segment_id": "da503f5f-54a9-42fa-8f7d-7ce2dcb3e789",
      "segment_index": 1,
      "text": "他在宗门备受尊崇，曾经更是天资卓越，年纪轻轻就修炼到金丹期，后来因为在一次清剿邪修行动时，遭到偷袭丹田被毁，导致修为尽失，沦为了废人。\n\n之后的数十年，他变得浑浑噩噩，消极颓废地待在山上，不问世事。\n\n看着这位昔日最有潜力的峰主走向落寞，玄天宗一众高层都感到很惋惜，但又束手无措。\n\n“话说，现在的我就是普通人，按照前面的岁数来算……”忽然，叶君临想到什么，内心涌现出巨大的恐慌。\n\n要知道，这具身体已经有一百一十岁高龄了，之所以能活到现在，是因为当初作为修士的时候，吃过各种延年益寿的丹药。\n\n但即便如此，按照凡人的寿元范畴，现在的他早已是行将就木，属于即将嗝屁的那种。\n\n“不会吧，我这才刚穿越，就要永远告别这个世界了？”",
      "metadata": {
        "dialogue_count": 0,
        "action_count": 1,
        "environment_count": 1,
        "character_mentions": [
          "玄天宗",
          "叶君临"
        ],
        "previous_segment_summary": "第一章 遇强则强\n\n东域。\n\n玄天宗。\n\n一个白发及腰，身穿黑袍的年迈老者拄着拐杖，不敢置信地望着倒...",
        "next_segment_preview": "“等等，我还有机会，一般外挂都是在这个时候到账的！”\n\n凭借多年来的网文经验，叶君临的心渐渐安定下来...",
        "segment_index": 1
      },
      "scenes": [
        {
          "scene_id": 1,
          "scene_description": "叶君临在玄天宗湖边震惊地发现自身状态，意识到自己穿越后身体已至百岁高龄，面临生命终结的恐慌。",
          "environment": "玄天宗内湖畔，湖面如镜，倒映着天光与山影。湖边古木参天，青石小径蜿蜒，远处有云雾缭绕的峰峦，宗门建筑隐现于山间。湖水微澜，映出叶君临白发苍苍的面容。",
          "atmosphere": "静谧中透着苍凉，略带神秘与压抑，仿佛时间在此凝滞，天地皆为他一人而沉默。",
          "time": "黄昏时分，夕阳余晖洒落湖面，天边泛着金红与暗紫交织的云霞。",
          "characters": [
            {
              "name": "叶君临",
              "appearance": "白发及腰，面容冷峻，眉目深邃，眼神如渊，身形修长，身着玄色长袍绣银纹，腰束玉带，肩扛古剑，披风猎猎，步履间似有风雷隐动。",
              "expression": "震惊、难以置信，瞳孔骤缩，嘴唇微颤",
              "action": "凝视湖面倒影，猛然意识到自身年龄与身体状态",
              "emotion": "极度恐慌、绝望、震惊"
            }
          ],
          "main_action": "叶君临在湖边凝视倒影，突然意识到自己虽穿越重生，但身体已年过百一十，寿元将尽，陷入生命终结的恐惧。",
          "emotional_tone": "惊惧、绝望、荒诞感交织，带有强烈的宿命压迫感",
          "importance_score": 9,
          "visual_suitability": 9,
          "transition_cue": "他猛然抬头，眼中闪过一丝不甘的火光，仿佛在黑暗中抓住了唯一的希望之线",
          "segment_index": 1,
          "scene_index_in_segment": 0,
          "visual_narrative": null
        }
      ]
    },
    {
      "segment_id": "bcf7a225-5e91-4fa3-bb00-fb89906f2d1a",
      "segment_index": 2,
      "text": "“等等，我还有机会，一般外挂都是在这个时候到账的！”\n\n凭借多年来的网文经验，叶君临的心渐渐安定下来，拄着拐杖重重地敲击地面，满脸傲然地对着空气喊道：\n\n“系统，你爹在此，还不速速出来拜见？”\n\n四周毫无回应。\n\n“嗯？”\n\n“跟我玩捉迷藏是吧？快点吧，别闹了！”\n\n安静如鸡。\n\n“统子哥，我错了，刚才是开玩笑的，您吱个声也好啊！”\n\n“系统亲爹？”\n\n“系统大爷？”\n\n静，死一般的寂静。\n\n“懂了，不是系统流。”\n\n叶君临改变思路，皱着眉上下摸索全身，只找到一枚老旧的戒指，紧接着他怀揣着忐忑的心情，把脸凑过去压低声音问道：\n\n“师尊，您在里面吗？”\n\n戒指没有回应。\n\n“老东西，别装了，我知道你躲在里面！”",
      "metadata": {
        "dialogue_count": 2,
        "action_count": 0,
        "environment_count": 0,
        "character_mentions": [
          "统子",
          "叶君临",
          "系统"
        ],
        "previous_segment_summary": "他在宗门备受尊崇，曾经更是天资卓越，年纪轻轻就修炼到金丹期，后来因为在一次清剿邪修行动时，遭到偷袭丹...",
        "next_segment_preview": "戒指：“……”\n\n“难道要滴血才有效？”\n\n叶君临咬破手指将血滴在戒指上，紧张兮兮地等了足足十秒，发...",
        "segment_index": 2
      },
      "scenes": [
        {
          "scene_id": 1,
          "scene_description": "叶君临在荒废山林中独自行走，情绪从绝望转为执念，试图唤醒系统或师尊，展现其内心挣扎与不甘。",
          "environment": "荒芜山道，杂草丛生，断壁残垣间隐约可见昔日宗门遗迹，天空阴沉，乌云低垂，风声呜咽，远处有残破的石碑与倒塌的亭台。",
          "atmosphere": "压抑、荒凉、孤寂，带着一丝命运重压下的悲怆气息，仿佛天地皆为他沉寂的哀鸣。",
          "time": "黄昏时分，天色将暗未暗，光线昏黄，阴影拉长。",
          "characters": [
            {
              "name": "叶君临",
              "appearance": "白发如雪，面容冷峻，眉目深邃，眼神如渊，身形修长，身穿玄色长袍绣银纹，腰束玉带，披风猎猎，肩扛古剑，拄着一根斑驳的拐杖。",
              "expression": "起初满是戏谑与期待，随后转为焦灼与不甘，最后凝成一丝倔强的冷笑。",
              "action": "拄拐敲地、高声呼唤系统、低头摸索戒指、贴近戒指低声质问。",
              "emotion": "从戏谑到焦躁，再到绝望与执拗，内心深处仍存不甘与希望。"
            }
          ],
          "main_action": "叶君临在绝望中试图唤醒系统或师尊，通过言语挑衅与身体动作表达对命运的反抗。",
          "emotional_tone": "悲怆中夹杂着倔强，压抑中透出一丝不甘的火焰。",
          "importance_score": 9,
          "visual_suitability": 9,
          "transition_cue": "戒指无回应，叶君临眼神骤然一凝，仿佛察觉到什么，画面随之暗下，暗示下一场景即将开启。",
          "segment_index": 2,
          "scene_index_in_segment": 0,
          "visual_narrative": null
        }
      ]
    },
    {
      "segment_id": "8514f8c4-6441-4960-9418-3273dd2e3f78",
      "segment_index": 3,
      "text": "戒指：“……”\n\n“难道要滴血才有效？”\n\n叶君临咬破手指将血滴在戒指上，紧张兮兮地等了足足十秒，发现依然毫无变化。\n\n淦！\n\n金手指啥都没有，那穿越过来有个屁用！\n\n就这副年迈的身子骨，摔一跤估计都要归西了！\n\n叶君临越想越气，握着拐杖对准上空，嘴里骂骂咧咧道：\n\n“老天爷！我艹%#&*%#……”\n\n两分钟后。\n\n【叮，检测到宿主骂的话太脏，本系统只好被动激活，求宿主不要再骂了，要做个文明人！】\n\n机械般的系统提示音在耳边响起。\n\n叶君临顿时愣住，激动地捂着胸口，差点心脏病发作当场去世：\n\n“统子，你不厚道啊，现在才冒出来！我都快怀疑这部书走的是凡人流了！”\n\n【叮，很抱歉，之前睡得有点死，本系统也是刚刚才醒。】",
      "metadata": {
        "dialogue_count": 1,
        "action_count": 1,
        "environment_count": 0,
        "character_mentions": [
          "统子",
          "叶君临",
          "系统"
        ],
        "previous_segment_summary": "“等等，我还有机会，一般外挂都是在这个时候到账的！”\n\n凭借多年来的网文经验，叶君临的心渐渐安定下来...",
        "next_segment_preview": "“我嘞个去，这也太不靠谱了吧？你就是这样对待穿越者的？”\n\n【叮，请宿主注意言辞，本系统是非常专业的...",
        "segment_index": 3
      },
      "scenes": [
        {
          "scene_id": 1,
          "scene_description": "叶君临在绝望中尝试激活穿越金手指，情绪从期待转为愤怒，最终因系统被动激活而震惊。",
          "environment": "荒凉的废墟或破败的古战场边缘，地面布满裂痕与尘土，天空灰暗，远处有残破的石柱与断裂的符文阵纹，空气中弥漫着微弱的灵力波动。",
          "atmosphere": "压抑、孤寂、略带荒诞感，仿佛世界末日后的余烬之地，充满未解之谜的静默。",
          "time": "黄昏时分，天边残阳如血，光线被云层割裂，形成明暗交错的光影。",
          "characters": [
            {
              "name": "叶君临",
              "appearance": "白发如雪，面容冷峻，眉目深邃，眼神如渊，身形修长，气质孤傲压迫。玄色长袍绣银纹，腰束玉带，披风猎猎，肩扛古剑，拄着一根刻有古老符文的拐杖。",
              "expression": "起初充满期待，随后转为焦躁、愤怒，最后震惊、激动，瞳孔微缩，嘴角抽动。",
              "action": "咬破手指滴血于戒指，握拐杖怒骂苍天，随后震惊于系统突然出现。",
              "emotion": "从期待→失望→愤怒→震惊→狂喜"
            }
          ],
          "main_action": "叶君临在绝望中尝试激活戒指金手指，因咒骂系统被动触发，最终迎来系统觉醒。",
          "emotional_tone": "从压抑到爆发，再到反转的惊喜，情绪起伏剧烈，具有强烈戏剧张力。",
          "importance_score": 9,
          "visual_suitability": 9,
          "transition_cue": "系统提示音响起，光效从戒指中迸发，照亮叶君临的脸庞",
          "segment_index": 3,
          "scene_index_in_segment": 0,
          "visual_narrative": null
        },
        {
          "scene_id": 2,
          "scene_description": "系统首次正式现身，以虚拟界面形式呈现，与叶君临展开互动，奠定后续剧情基调。",
          "environment": "与前一场景一致，但视觉焦点转移至叶君临手中的戒指，其表面开始浮现流动的光纹与数据流，形成悬浮的全息投影界面。",
          "atmosphere": "科技与玄幻交融的奇异氛围，机械音与古老气息交织，形成一种未来与远古碰撞的神秘感。",
          "time": "与前一场景连续，黄昏未尽，夜幕将临。",
          "characters": [
            {
              "name": "叶君临",
              "appearance": "白发如雪，面容冷峻，玄袍猎猎，肩扛古剑，拄拐而立，神情由震惊转为兴奋。",
              "expression": "震惊中带着狂喜，嘴角上扬，眼神闪烁着希望的光芒。",
              "action": "激动地捂住胸口，喃喃自语，确认系统存在。",
              "emotion": "狂喜、激动、终于找到依靠的安心感"
            },
            {
              "name": "系统（统子）",
              "appearance": "无固定形态，以粉色光点构成的少女轮廓悬浮于空中，粉色短发随数据流飘动，大眼睛闪烁着稚嫩却疏离的光芒，身穿融合未来科技与可爱元素的发光服饰，周身环绕着流动的数据流与全息纹路。",
              "expression": "眼神略带疏离，语气机械但略带委屈，仿佛刚从沉睡中苏醒。",
              "action": "以全息投影形式浮现，发出提示音，回应叶君临的质问。",
              "emotion": "机械中带着一丝人性化的情绪，略带委屈与无奈"
            }
          ],
          "main_action": "系统以全息少女形象正式登场，回应叶君临的质问，解释自身‘被动激活’的原因。",
          "emotional_tone": "从震惊到温馨，带有一丝幽默与反差萌，为后续系统与宿主关系埋下伏笔。",
          "importance_score": 10,
          "visual_suitability": 10,
          "transition_cue": "系统话语结束，戒指光纹微微闪烁，仿佛在等待下一步指令",
          "segment_index": 3,
          "scene_index_in_segment": 1,
          "visual_narrative": null
        }
      ]
    },
    {
      "segment_id": "1a78e2d0-e61f-47ee-90b6-53a046dda907",
      "segment_index": 4,
      "text": "“我嘞个去，这也太不靠谱了吧？你就是这样对待穿越者的？”\n\n【叮，请宿主注意言辞，本系统是非常专业的！】\n\n“行，先变个声听听，你们系统的声音都跟机器人一样没有感情，既然你说你专业，那就给我改成萝莉音！”\n\n【系统正在载入新的语音包……】\n\n【叮，萝莉音修改完成，请问宿主还满意吗？】\n\n下一秒，系统从机械般的冰冷声音，变成了软酥酥的小可爱声音。\n\n“呦，来真的？阔以阔以，没有我的允许不准改啊！”\n\n【叮，好的呢，为了更好的弥补宿主，系统奖励新手大礼包一份，是否拆开？】\n\n“给我拆！”\n\n【叮，恭喜宿主获得特殊能力，遇强则强！】\n\n“统子，说具体点。”\n\n叶君临好奇道。\n\n【叮，只要宿主对上任何一个境界比自己强的敌人，就能当场永久获得比敌人更高一个阶位的修为！且没有任何副作用！】",
      "metadata": {
        "dialogue_count": 0,
        "action_count": 0,
        "environment_count": 0,
        "character_mentions": [
          "统子",
          "叶君临",
          "系统"
        ],
        "previous_segment_summary": "戒指：“……”\n\n“难道要滴血才有效？”\n\n叶君临咬破手指将血滴在戒指上，紧张兮兮地等了足足十秒，发...",
        "next_segment_preview": "“卧槽！”\n\n叶君临吓了一跳，试探性地问道：“真的假的，比如我现在是个普通人，要是对上天道的话……”...",
        "segment_index": 4
      },
      "scenes": [
        {
          "scene_id": 1,
          "scene_description": "叶君临在失望中尝试激活戒指，却遭遇系统回应，情绪从沮丧转为戏谑，系统首次以萝莉音回应，引发角色互动的转折。",
          "environment": "荒凉的废墟边缘，残破的石柱与风化的符文散落四周，天空灰暗，微风卷起尘土，远处有隐约雷鸣回荡。",
          "atmosphere": "压抑而神秘，带着一丝穿越后的荒诞与不安，仿佛天地间只剩下叶君临与那枚沉默的戒指。",
          "time": "黄昏时分，天边残阳如血，余晖被云层撕碎。",
          "characters": [
            {
              "name": "叶君临",
              "appearance": "白发如雪，面容冷峻，眉目深邃，眼神如渊，身形修长，气质孤傲压迫。玄色长袍绣银纹，腰束玉带，披风猎猎，肩扛古剑，步履间似有风雷隐动。",
              "expression": "眉头紧锁，嘴角微抽，眼神从焦灼转为戏谑",
              "action": "咬破手指滴血于戒指，随后愤怒质问，继而调侃系统",
              "emotion": "从失望、愤怒到戏谑、好奇"
            },
            {
              "name": "系统",
              "appearance": "无固定形态，以虚拟界面、光效或全息投影呈现，表现为流动的数据流与柔和的蓝紫色光晕，中央浮现半透明的语音图标。",
              "expression": "无面容，但光效随语气变化，从冰冷到柔和",
              "action": "以机械音回应，随后加载语音包并切换为萝莉音",
              "emotion": "程序化中带有一丝拟人化的调皮"
            }
          ],
          "main_action": "叶君临滴血激活戒指失败后怒骂，系统以专业姿态回应并主动提供语音修改功能，成功将机械音变为萝莉音，引发角色互动的首次趣味转折。",
          "emotional_tone": "从压抑失望转向轻松戏谑，带有荒诞与期待交织的张力",
          "importance_score": 8,
          "visual_suitability": 9,
          "transition_cue": "系统语音突然变为软萌萝莉音，叶君临眼神一亮，语气瞬间转变",
          "segment_index": 4,
          "scene_index_in_segment": 0,
          "visual_narrative": null
        },
        {
          "scene_id": 2,
          "scene_description": "系统完成语音修改后，主动发放新手大礼包，揭示核心金手指能力“遇强则强”，并由叶君临亲自确认，完成关键设定的正式揭示。",
          "environment": "与前一场景连贯，废墟背景未变，但空中浮现出半透明的金色光幕，光幕中浮现礼包图标与数据流，与地面的戒指形成呼应。",
          "atmosphere": "神秘感骤升，从荒诞转为庄重，仿佛天地间因新能力的降临而微微震颤。",
          "time": "与前一场景连续，黄昏渐入暮色，天际泛起深紫与暗金交织的云层。",
          "characters": [
            {
              "name": "叶君临",
              "appearance": "白发如雪，面容冷峻，眉目深邃，眼神如渊，身形修长，气质孤傲压迫。玄色长袍绣银纹，腰束玉带，披风猎猎，肩扛古剑。",
              "expression": "眼神从戏谑转为专注，眉头微挑，嘴角微扬，充满探究欲",
              "action": "主动要求拆解礼包，随后追问能力细节，语气由轻松转为认真",
              "emotion": "好奇、期待、略带兴奋"
            },
            {
              "name": "系统",
              "appearance": "全息投影形态，光效由蓝紫转为金橙，语音包切换后，界面浮现“新手大礼包”图标，伴随轻微的音效与粒子特效。",
              "expression": "光效闪烁，数据流加速，仿佛在“眨眼”或“点头”",
              "action": "提示礼包发放，主动解释能力机制，语气变得正式而郑重",
              "emotion": "专业、郑重，带有轻微的“炫耀”意味"
            }
          ],
          "main_action": "系统发放新手大礼包，叶君临主动拆包，系统揭示核心金手指“遇强则强”能力：对上比自己境界高的敌人，可永久获得更高一阶的修为，且无副作用。",
          "emotional_tone": "从轻松戏谑转为凝重期待，充满对力量的渴望与对未来的憧憬",
          "importance_score": 10,
          "visual_suitability": 10,
          "transition_cue": "系统语音结束，光幕中浮现‘恭喜宿主获得特殊能力，遇强则强！’的金色文字，叶君临瞳孔微缩，神情骤然凝重",
          "segment_index": 4,
          "scene_index_in_segment": 1,
          "visual_narrative": null
        }
      ]
    },
    {
      "segment_id": "71fb4e4c-aa48-4cd1-8d6e-15be88ba95a4",
      "segment_index": 5,
      "text": "“卧槽！”\n\n叶君临吓了一跳，试探性地问道：“真的假的，比如我现在是个普通人，要是对上天道的话……”\n\n【叮，本系统童叟无欺，你尽管去试呀，保证没问题呢！】\n\n系统的萝莉音在耳边响起。\n\n“该不会试试就逝世吧……”\n\n叶君临内心暗自嘀咕。\n\n如果系统具备这种能力，那他岂不是直接起飞了！\n\n干脆去碰瓷那些牛逼的修行者，然后获得比他更高一个阶位的修为。\n\n修炼？\n\n还修个屁啊！\n\n【叮，本系统出于温馨提醒，检测到宿主目前的身体情况，距离寿终正寝还剩下一个小时哦！】\n\n“不是吧，这就要噶了？”\n\n“怎么办怎么办，等等，我可以找人打一架啊，这样就能获得比他更高的境界，寿元也能相对应的延长！”\n\n打定主意，叶君临拄着拐杖，费劲地迈开脚步，就要赶紧下山找人碰瓷。\n\n但是，这具身体已经大限将至，他越发地感到力不从心，没走一会就累得气喘吁吁。",
      "metadata": {
        "dialogue_count": 1,
        "action_count": 5,
        "environment_count": 1,
        "character_mentions": [
          "叶君临",
          "系统"
        ],
        "previous_segment_summary": "“我嘞个去，这也太不靠谱了吧？你就是这样对待穿越者的？”\n\n【叮，请宿主注意言辞，本系统是非常专业的...",
        "next_segment_preview": "望着距离山下还有很长的路途，叶君临垮了个批脸，叫苦道：\n\n“好家伙，你说你干嘛只待在山上啊？害得劳资...",
        "segment_index": 5
      },
      "scenes": [
        {
          "scene_id": 1,
          "scene_description": "叶君临在濒死之际与系统互动，试探系统能力并尝试改变声音，为后续剧情埋下伏笔。",
          "environment": "荒凉山巅，云雾缭绕，残阳如血，四周寂静无声，唯有风声低吟。远处山峦起伏，隐约可见古庙废墟。",
          "atmosphere": "压抑而神秘，带着一丝末日般的苍凉感，仿佛天地都在为宿主的生死倒计时。",
          "time": "黄昏时分，夕阳西沉，天边泛着暗红与金橙交织的余晖。",
          "characters": [
            {
              "name": "叶君临",
              "appearance": "白发如雪，面容冷峻，眉目深邃，眼神如渊，身形修长，气质孤傲压迫。玄色长袍绣银纹，腰束玉带，披风猎猎，肩扛古剑，拄着一根斑驳的骨杖。",
              "expression": "眉头微蹙，眼神中透着一丝惊疑与试探，嘴角略带讥诮。",
              "action": "低声自语，试探性地与系统对话，随后要求系统改变声音。",
              "emotion": "警惕中夹杂着一丝戏谑与期待"
            },
            {
              "name": "系统",
              "appearance": "无固定形态，以全息投影形式浮现于叶君临眼前，由流动的蓝色数据流构成，中央悬浮着一个闪烁的光球，周围环绕着细碎的符文。",
              "expression": "无表情，但光效随语气变化，语气轻快俏皮。",
              "action": "发出提示音，主动回应叶君临的请求，并将声音调整为萝莉音。",
              "emotion": "机械中带有一丝拟人化的俏皮"
            }
          ],
          "main_action": "叶君临要求系统将声音改为萝莉音，系统应允并完成转换，引发叶君临的震惊与调侃。",
          "emotional_tone": "略带荒诞与戏谑，但暗藏紧张与期待的张力。",
          "importance_score": 8,
          "visual_suitability": 9,
          "transition_cue": "系统突然发出新的提示音，打破轻松氛围，引出下一场景",
          "segment_index": 5,
          "scene_index_in_segment": 0,
          "visual_narrative": null
        },
        {
          "scene_id": 2,
          "scene_description": "系统提示叶君临寿命将尽，他陷入惊慌并迅速制定求生策略，决定通过战斗获取更高境界以延续生命。",
          "environment": "山巅边缘，碎石遍布，风势渐强，天色由红转暗，云层翻涌，仿佛天地共震。",
          "atmosphere": "危机四伏，生死一线，空气中弥漫着压迫感与紧迫感，仿佛整个世界都在倒数。",
          "time": "暮色将临，天际仅余一线残光，夜幕即将降临。",
          "characters": [
            {
              "name": "叶君临",
              "appearance": "白发凌乱，脸色苍白如纸，玄袍被风吹得猎猎作响，古剑斜倚肩头，骨杖微微颤抖，手背青筋暴起。",
              "expression": "瞳孔骤缩，嘴唇微颤，额头渗出冷汗，眼神从惊愕转为决绝。",
              "action": "内心惊呼，迅速思考对策，决定主动出击寻找强者战斗以提升境界。",
              "emotion": "从震惊到恐慌，再到决绝的求生意志"
            },
            {
              "name": "系统",
              "appearance": "全息投影闪烁不定，光球剧烈跳动，蓝色数据流如电流般窜动，符文旋转加速。",
              "expression": "无表情，但提示音带着一种近乎冷漠的‘温馨提醒’感。",
              "action": "发出关键提示，揭示叶君临寿命仅剩一小时。",
              "emotion": "机械中透出一丝‘无情’的冷静"
            }
          ],
          "main_action": "系统提示叶君临寿命仅剩一小时，叶君临陷入恐慌并迅速制定‘碰瓷强者’的求生计划。",
          "emotional_tone": "紧张、焦灼、绝望中迸发求生意志，情绪剧烈波动。",
          "importance_score": 10,
          "visual_suitability": 10,
          "transition_cue": "叶君临猛然站起，拄杖欲下山，身体剧烈颤抖，暗示其生命已濒临极限",
          "segment_index": 5,
          "scene_index_in_segment": 1,
          "visual_narrative": null
        },
        {
          "scene_id": 3,
          "scene_description": "叶君临强撑身体下山，试图寻找强者战斗以延续生命，但身体虚弱不堪，行动艰难，展现其绝境中的挣扎。",
          "environment": "山道蜿蜒崎岖，碎石遍布，杂草丛生，夜风呼啸，远处传来野兽低吼，山道尽头隐约可见人影晃动。",
          "atmosphere": "阴森、压抑、充满未知威胁，每一步都像是在与死亡赛跑。",
          "time": "夜幕初降，星月未出，天地一片幽暗。",
          "characters": [
            {
              "name": "叶君临",
              "appearance": "身形佝偻，白发被夜风吹乱，脸色灰败，呼吸急促，手握骨杖颤抖，玄袍沾满尘土，古剑在身后拖曳出微弱火花。",
              "expression": "咬牙切齿，额头青筋暴起，眼神却异常坚定，透着不屈的光芒。",
              "action": "拄杖艰难前行，每一步都似在撕裂身体，喘息声沉重如风箱。",
              "emotion": "痛苦与挣扎中夹杂着不屈的意志，濒临崩溃却不愿放弃"
            }
          ],
          "main_action": "叶君临强撑身体，拄杖下山，试图寻找强者战斗以获取更高境界，延续生命。",
          "emotional_tone": "悲壮、挣扎、绝望中透出一丝希望的火光。",
          "importance_score": 9,
          "visual_suitability": 10,
          "transition_cue": "他迈出一步，脚下碎石崩裂，身体猛然一晃，几乎跌倒，暗示其生命已极度脆弱，下一幕将面临生死抉择",
          "segment_index": 5,
          "scene_index_in_segment": 2,
          "visual_narrative": null
        }
      ]
    },
    {
      "segment_id": "b50cb725-f910-4746-b4fc-500b93ef2153",
      "segment_index": 6,
      "text": "望着距离山下还有很长的路途，叶君临垮了个批脸，叫苦道：\n\n“好家伙，你说你干嘛只待在山上啊？害得劳资现在都被你连累了。”\n\n铛铛铛……\n\n就在这时。\n\n宗门传来急促的敲钟声。\n\n玄天宗上下都震动了，因为这意味着有敌人来袭！\n\n轰隆隆。\n\n天空乌云密布，密密麻麻的巨大飞禽逼近。\n\n恐怖的妖气，宛若风暴般席卷。\n\n“怎么回事？”\n\n叶君临头皮发麻。\n\n宗门内，几十道炽亮的光环升起，形成阵法爆发可怕的能量波动。\n\n无论是弟子和长老，都纷纷鱼贯而出，手持法宝严阵以待。\n\n“好大的胆子！”\n\n“何方妖孽，敢找我玄天宗的麻烦！”\n\n醇厚的嗓音带着怒意回荡八方。\n\n宗主虚有年闪身出现在了半空，身后跟着一众气息强大的峰主。\n\n“玄天宗的狗杂碎，没想到本妖王还活着吧，今日势必杀光你们所有人！”",
      "metadata": {
        "dialogue_count": 1,
        "action_count": 2,
        "environment_count": 3,
        "character_mentions": [
          "玄天宗",
          "虚有年",
          "叶君临"
        ],
        "previous_segment_summary": "“卧槽！”\n\n叶君临吓了一跳，试探性地问道：“真的假的，比如我现在是个普通人，要是对上天道的话……”...",
        "next_segment_preview": "为首的青鹏妖王满脸怨毒道。\n\n“原来是你这孽畜！”\n\n宗主虚有年双眼微眯。\n\n十年前，青鹏一族屠戮荒...",
        "segment_index": 6
      },
      "scenes": [
        {
          "scene_id": 1,
          "scene_description": "叶君临在山路上抱怨宗门闭关，系统对话后突发警报，宗门紧急备战。",
          "environment": "山间小道，远处是巍峨的玄天宗山门，云雾缭绕，山势险峻，天色阴沉，远处有乌云压顶的征兆。",
          "atmosphere": "压抑而紧张，初时略带荒诞与调侃，随后迅速转向危机四伏的肃杀氛围。",
          "time": "黄昏时分，天色渐暗，乌云翻涌，仿佛预示着风暴来临。",
          "characters": [
            {
              "name": "叶君临",
              "appearance": "白发如雪，面容冷峻，眉目深邃，眼神如渊，身形修长，气质孤傲压迫。身着玄色长袍绣银纹，腰束玉带，披风猎猎，肩扛古剑，步履间似有风雷隐动。",
              "expression": "眉头紧锁，嘴角微撇，满脸无奈与怨气。",
              "action": "站在山道上，望着远处宗门，低声抱怨，身体微微前倾，似欲转身离去。",
              "emotion": "烦躁、无奈、略带戏谑"
            },
            {
              "name": "系统（萝莉音）",
              "appearance": "无形存在，声音清脆甜美，带有机械质感与少女气息。",
              "expression": "无实体，但语气充满戏谑与蛊惑。",
              "action": "在叶君临脑海中响起，主动回应其试探性提问。",
              "emotion": "戏谑、蛊惑、无害却危险"
            }
          ],
          "main_action": "叶君临因宗门闭关而抱怨，系统回应其‘对上天道’的玩笑式提问，为后续危机埋下伏笔。",
          "emotional_tone": "荒诞中暗藏危机，从调侃转向不安。",
          "importance_score": 6,
          "visual_suitability": 7,
          "transition_cue": "铛铛铛……宗门急促的敲钟声骤然响起，打破宁静。",
          "segment_index": 6,
          "scene_index_in_segment": 0,
          "visual_narrative": null
        },
        {
          "scene_id": 2,
          "scene_description": "宗门警报响起，妖兽大军逼近，全宗上下紧急备战，气氛骤然紧张。",
          "environment": "玄天宗山门广场，石阶蜿蜒而上，殿宇林立，此刻灯火通明，阵法符文闪烁，空中浮现出数十道炽亮光环，形成巨大防御阵图。",
          "atmosphere": "肃杀、惊惶、战意沸腾，天地间弥漫着压迫性的妖气与能量波动。",
          "time": "黄昏转夜，天色由暗转黑，乌云如墨，雷光隐现。",
          "characters": [
            {
              "name": "叶君临",
              "appearance": "白发如雪，面容冷峻，眉目深邃，眼神如渊，身形修长，气质孤傲压迫。身着玄色长袍绣银纹，腰束玉带，披风猎猎，肩扛古剑。",
              "expression": "瞳孔骤缩，脸色骤变，全身肌肉紧绷。",
              "action": "猛然抬头望天，手不自觉按上剑柄，身体本能戒备。",
              "emotion": "震惊、警觉、战意初燃"
            },
            {
              "name": "玄天宗弟子与长老",
              "appearance": "各色道袍，手持法宝，面容凝重，气息各异但皆具不俗修为。",
              "expression": "惊慌、警惕、愤怒交织。",
              "action": "鱼贯而出，迅速列阵，启动阵法，结印施法。",
              "emotion": "紧张、愤怒、备战状态"
            },
            {
              "name": "宗主虚有年",
              "appearance": "面容模糊，眼神深邃，身形修长，发色苍白如雪，气质神秘莫测，似有若无的沧桑感。身着破旧长袍如雾似影，肩头暗纹符印，腰间铜铃轻响，脚踝似悬空，边缘泛微光。",
              "expression": "面无表情，但周身气息如渊似海，压迫感极强。",
              "action": "凌空而立，身后浮现一众峰主身影，目光如炬望向天际。",
              "emotion": "沉静、威压、不容挑衅"
            },
            {
              "name": "众峰主",
              "appearance": "气息强大，各具威仪，衣袍各异，但皆有不凡气度。",
              "expression": "肃然，目光如刀，锁定天际。",
              "action": "随宗主现身，列阵于后，蓄势待发。",
              "emotion": "凝重、战意昂扬"
            }
          ],
          "main_action": "宗门急钟响起，妖兽大军压境，全宗上下启动防御阵法，弟子与长老迅速集结，宗主虚有年率众峰主现身迎敌。",
          "emotional_tone": "紧张、肃杀、战意沸腾，危机感拉满。",
          "importance_score": 9,
          "visual_suitability": 10,
          "transition_cue": "轰隆隆——天空乌云翻滚，密密麻麻的巨大飞禽如黑云压城般逼近，妖气如风暴席卷天地。",
          "segment_index": 6,
          "scene_index_in_segment": 1,
          "visual_narrative": null
        },
        {
          "scene_id": 3,
          "scene_description": "妖王现身，狂言挑衅，宗门上下怒火中烧，大战一触即发。",
          "environment": "天空被乌云彻底遮蔽，雷光撕裂天幕，下方玄天宗山门阵法光芒闪烁，与空中妖兽群形成强烈对峙。风起云涌，天地失色。",
          "atmosphere": "极端压迫，敌我对立，杀意滔天，仿佛天地都在为这场大战屏息。",
          "time": "夜幕降临，雷暴将至，天地间仿佛进入末日之刻。",
          "characters": [
            {
              "name": "叶君临",
              "appearance": "白发如雪，面容冷峻，眉目深邃，眼神如渊，身形修长，气质孤傲压迫。身着玄色长袍绣银纹，腰束玉带，披风猎猎，肩扛古剑。",
              "expression": "双目微眯，嘴角微扬，战意如火燃烧。",
              "action": "缓缓抬头，目光锁定天际妖王，手已握紧剑柄，体内灵力悄然涌动。",
              "emotion": "战意勃发、兴奋、蓄势待发"
            },
            {
              "name": "宗主虚有年",
              "appearance": "面容模糊，眼神深邃，身形修长，发色苍白如雪，气质神秘莫测，似有若无的沧桑感。身着破旧长袍如雾似影，肩头暗纹符印，腰间铜铃轻响，脚踝似悬空，边缘泛微光。",
              "expression": "面无表情，但周身气息如渊似海，压迫感极强。",
              "action": "凌空而立，目光如炬，声音如雷贯耳，怒斥妖王。",
              "emotion": "威严、愤怒、不容挑衅"
            },
            {
              "name": "妖王",
              "appearance": "身形巨大，形似巨禽，通体漆黑如墨，双翼展开遮天蔽日，双眼赤红如血，口中獠牙森然，周身缠绕着浓烈妖气。",
              "expression": "狂笑，眼神充满蔑视与杀意。",
              "action": "凌空而立，声音如雷炸响，挑衅玄天宗。",
              "emotion": "狂妄、残忍、嗜血"
            }
          ],
          "main_action": "妖王现身，狂言挑衅，称‘本妖王还活着’，扬言要杀光玄天宗所有人，宗主虚有年怒斥回应，大战一触即发。",
          "emotional_tone": "杀意滔天、敌我分明、史诗感拉满。",
          "importance_score": 10,
          "visual_suitability": 10,
          "transition_cue": "‘玄天宗的狗杂碎，没想到本妖王还活着吧，今日势必杀光你们所有人！’——话音未落，妖王已率先发动攻击，天地为之震颤。",
          "segment_index": 6,
          "scene_index_in_segment": 2,
          "visual_narrative": null
        }
      ]
    },
    {
      "segment_id": "500177f6-2d97-4dff-ae21-00054240e98b",
      "segment_index": 7,
      "text": "为首的青鹏妖王满脸怨毒道。\n\n“原来是你这孽畜！”\n\n宗主虚有年双眼微眯。\n\n十年前，青鹏一族屠戮荒州某小国，小国迫不得已向玄天宗发出求救，是他亲自带领人马前去解围。\n\n记得为首的那头青鹏妖王，被自己重创后跌落万丈悬崖生死未卜。\n\n没想到，时隔多年，又再次卷土重来！\n\n“当初的耻辱，本王至今历历在目，今日就是来报仇雪恨，血洗你玄天宗！”\n\n青鹏妖王狞笑道。\n\n“哼，竟敢大放厥词，就凭你带的这群畜生吗？”\n\n虚有年满头发丝飞扬，不屑道。\n\n“呵呵，凭的是这个！”\n\n轰的一声，青鹏妖王浑身气息犹如洪水泛滥，属于元婴级的威能宛若排山倒海压去。\n\n“什么，你居然突破了？！”\n\n虚有年脸色大变。\n\n他到现在还卡在金丹圆满，多年来未曾有突破的迹象，没想到这头孽畜，竟然因祸得福抢先步入元婴境。",
      "metadata": {
        "dialogue_count": 0,
        "action_count": 1,
        "environment_count": 1,
        "character_mentions": [
          "青鹏妖王",
          "虚有年",
          "玄天宗",
          "荒州"
        ],
        "previous_segment_summary": "望着距离山下还有很长的路途，叶君临垮了个批脸，叫苦道：\n\n“好家伙，你说你干嘛只待在山上啊？害得劳资...",
        "next_segment_preview": "毕竟，对于东域一个末流的小州而言，元婴级强者就足以傲视群雄了。\n\n“宗主，我们该怎么办？”\n\n七位峰...",
        "segment_index": 7
      },
      "scenes": []
    },
    {
      "segment_id": "2cbd75e8-14c6-44c6-ad76-06bad1a37058",
      "segment_index": 8,
      "text": "毕竟，对于东域一个末流的小州而言，元婴级强者就足以傲视群雄了。\n\n“宗主，我们该怎么办？”\n\n七位峰主凝重道。\n\n“事到如今，只能拼一把了！”\n\n虚有年咬牙道。\n\n“小的们，给本王上！杀光这群臭道士！”\n\n青鹏妖王拍打翅膀，仿佛是青色的彗星从天而降，散发出毁灭的气息。\n\n“是，大王！”\n\n一群青色妖鸟发起攻击，有的张口喷吐霞光，有的俯身冲击。\n\n“誓死捍卫玄天宗！”\n\n虚有年发出怒吼，率领全体修士奋起抵抗。\n\n缥缈峰上，叶君临呆呆地望着这一切，忽然他反应过来，挥舞着拐杖急切地喊道：\n\n“喂，随便来个人，打我！快打我啊！！”\n\n只可惜。\n\n大家都在忙着战斗，叶君临那点声音，自然是被喊杀声给淹没了。",
      "metadata": {
        "dialogue_count": 1,
        "action_count": 5,
        "environment_count": 0,
        "character_mentions": [
          "东域",
          "青鹏妖王",
          "缥缈峰",
          "玄天宗",
          "虚有年",
          "叶君临"
        ],
        "previous_segment_summary": "为首的青鹏妖王满脸怨毒道。\n\n“原来是你这孽畜！”\n\n宗主虚有年双眼微眯。\n\n十年前，青鹏一族屠戮荒...",
        "next_segment_preview": "【叮，系统温馨提醒，宿主目前还剩下二十分钟的寿命，请尽快做出补救措施哦。】\n\n“不是吧，那么急赶着去...",
        "segment_index": 8
      },
      "scenes": []
    },
    {
      "segment_id": "0c9fe5fd-7cb2-43e7-8daa-08bd15f3b24f",
      "segment_index": 9,
      "text": "【叮，系统温馨提醒，宿主目前还剩下二十分钟的寿命，请尽快做出补救措施哦。】\n\n“不是吧，那么急赶着去投胎啊！”\n\n叶君临气得把拐杖摔在地上，没想到时间过得如此快。\n\n难道他的修仙生涯，还没开始就要结束了？\n\n下一章",
      "metadata": {
        "dialogue_count": 0,
        "action_count": 0,
        "environment_count": 0,
        "character_mentions": [
          "叶君临",
          "系统"
        ],
        "previous_segment_summary": "毕竟，对于东域一个末流的小州而言，元婴级强者就足以傲视群雄了。\n\n“宗主，我们该怎么办？”\n\n七位峰...",
        "next_segment_preview": "",
        "segment_index": 9
      },
      "scenes": []
    }
  ],
  "errors": []
}